[
  {
    "id": 1001,
    "IOCPLLBAMDH": 1,
    "CMCLFNNNLNL": 1,
    "NFMNMGAFIJI": 1768065800,
    "MBCOKNPMNFK": "No problem!",
    "icon": "UI_EmotionIcon1"
  },
  {
    "id": 1002,
    "IOCPLLBAMDH": 1,
    "CMCLFNNNLNL": 2,
    "NFMNMGAFIJI": 1137090424,
    "MBCOKNPMNFK": "Ship out!",
    "icon": "UI_EmotionIcon2"
  },
  {
    "id": 1003,
    "IOCPLLBAMDH": 1,
    "CMCLFNNNLNL": 3,
    "NFMNMGAFIJI": 2751037024,
    "MBCOKNPMNFK": "Hehe~",
    "icon": "UI_EmotionIcon3"
  },
  {
    "id": 1004,
    "IOCPLLBAMDH": 1,
    "CMCLFNNNLNL": 4,
    "NFMNMGAFIJI": 1747701768,
    "MBCOKNPMNFK": "Time to eat!",
    "icon": "UI_EmotionIcon4"
  },
  {
    "id": 1005,
    "IOCPLLBAMDH": 1,
    "CMCLFNNNLNL": 5,
    "NFMNMGAFIJI": 3974698384,
    "MBCOKNPMNFK": "Surprised!",
    "icon": "UI_EmotionIcon5"
  },
  {
    "id": 1006,
    "IOCPLLBAMDH": 1,
    "CMCLFNNNLNL": 6,
    "NFMNMGAFIJI": 4184519584,
    "MBCOKNPMNFK": "Too easy!",
    "icon": "UI_EmotionIcon6"
  },
  {
    "id": 1007,
    "IOCPLLBAMDH": 1,
    "CMCLFNNNLNL": 7,
    "NFMNMGAFIJI": 1700899640,
    "MBCOKNPMNFK": "Noooo!",
    "icon": "UI_EmotionIcon7"
  },
  {
    "id": 1008,
    "IOCPLLBAMDH": 1,
    "CMCLFNNNLNL": 8,
    "NFMNMGAFIJI": 2298843480,
    "MBCOKNPMNFK": "Oh...",
    "icon": "UI_EmotionIcon8"
  },
  {
    "id": 1009,
    "IOCPLLBAMDH": 1,
    "CMCLFNNNLNL": 9,
    "NFMNMGAFIJI": 649207328,
    "MBCOKNPMNFK": "Well done!",
    "icon": "UI_EmotionIcon9"
  },
  {
    "id": 1010,
    "IOCPLLBAMDH": 1,
    "CMCLFNNNLNL": 10,
    "NFMNMGAFIJI": 2848677536,
    "MBCOKNPMNFK": "Save me!",
    "icon": "UI_EmotionIcon10"
  },
  {
    "id": 1011,
    "IOCPLLBAMDH": 1,
    "CMCLFNNNLNL": 11,
    "NFMNMGAFIJI": 224169832,
    "MBCOKNPMNFK": "That's funny!",
    "icon": "UI_EmotionIcon11"
  },
  {
    "id": 1012,
    "IOCPLLBAMDH": 1,
    "CMCLFNNNLNL": 12,
    "NFMNMGAFIJI": 2595736264,
    "MBCOKNPMNFK": "Outta my way!",
    "icon": "UI_EmotionIcon12"
  },
  {
    "id": 1013,
    "IOCPLLBAMDH": 1,
    "CMCLFNNNLNL": 13,
    "NFMNMGAFIJI": 1696903856,
    "MBCOKNPMNFK": "Fall asleep",
    "icon": "UI_EmotionIcon13"
  },
  {
    "id": 1014,
    "IOCPLLBAMDH": 1,
    "CMCLFNNNLNL": 14,
    "NFMNMGAFIJI": 240117128,
    "MBCOKNPMNFK": "Please~",
    "icon": "UI_EmotionIcon14"
  },
  {
    "id": 1015,
    "IOCPLLBAMDH": 1,
    "CMCLFNNNLNL": 15,
    "NFMNMGAFIJI": 4193107520,
    "MBCOKNPMNFK": "Alert",
    "icon": "UI_EmotionIcon15"
  },
  {
    "id": 1016,
    "IOCPLLBAMDH": 1,
    "CMCLFNNNLNL": 16,
    "NFMNMGAFIJI": 1594612128,
    "MBCOKNPMNFK": "Will 1 Mora do?",
    "icon": "UI_EmotionIcon16"
  },
  {
    "id": 2001,
    "IOCPLLBAMDH": 2,
    "CMCLFNNNLNL": 17,
    "NFMNMGAFIJI": 907866040,
    "MBCOKNPMNFK": "OK",
    "icon": "UI_EmotionIcon17"
  },
  {
    "id": 2002,
    "IOCPLLBAMDH": 2,
    "CMCLFNNNLNL": 18,
    "NFMNMGAFIJI": 297422784,
    "MBCOKNPMNFK": "I'll be good",
    "icon": "UI_EmotionIcon18"
  },
  {
    "id": 2003,
    "IOCPLLBAMDH": 2,
    "CMCLFNNNLNL": 19,
    "NFMNMGAFIJI": 3557242952,
    "MBCOKNPMNFK": "Doubt",
    "icon": "UI_EmotionIcon19"
  },
  {
    "id": 2004,
    "IOCPLLBAMDH": 2,
    "CMCLFNNNLNL": 20,
    "NFMNMGAFIJI": 154645112,
    "MBCOKNPMNFK": "Shame",
    "icon": "UI_EmotionIcon20"
  },
  {
    "id": 2005,
    "IOCPLLBAMDH": 2,
    "CMCLFNNNLNL": 21,
    "NFMNMGAFIJI": 1725448560,
    "MBCOKNPMNFK": "Love",
    "icon": "UI_EmotionIcon21"
  },
  {
    "id": 2006,
    "IOCPLLBAMDH": 2,
    "CMCLFNNNLNL": 22,
    "NFMNMGAFIJI": 4029106776,
    "MBCOKNPMNFK": "Hehe",
    "icon": "UI_EmotionIcon22"
  },
  {
    "id": 2007,
    "IOCPLLBAMDH": 2,
    "CMCLFNNNLNL": 23,
    "NFMNMGAFIJI": 1697493024,
    "MBCOKNPMNFK": "Like",
    "icon": "UI_EmotionIcon23"
  },
  {
    "id": 2008,
    "IOCPLLBAMDH": 2,
    "CMCLFNNNLNL": 24,
    "NFMNMGAFIJI": 2233609800,
    "MBCOKNPMNFK": "Good Night",
    "icon": "UI_EmotionIcon24"
  },
  {
    "id": 2009,
    "IOCPLLBAMDH": 2,
    "CMCLFNNNLNL": 25,
    "NFMNMGAFIJI": 2750612488,
    "MBCOKNPMNFK": "Fallen",
    "icon": "UI_EmotionIcon25"
  },
  {
    "id": 2010,
    "IOCPLLBAMDH": 2,
    "CMCLFNNNLNL": 26,
    "NFMNMGAFIJI": 992918520,
    "MBCOKNPMNFK": "Secretly observing",
    "icon": "UI_EmotionIcon26"
  },
  {
    "id": 2011,
    "IOCPLLBAMDH": 2,
    "CMCLFNNNLNL": 27,
    "NFMNMGAFIJI": 704834136,
    "MBCOKNPMNFK": "Oh!",
    "icon": "UI_EmotionIcon27"
  },
  {
    "id": 2012,
    "IOCPLLBAMDH": 2,
    "CMCLFNNNLNL": 28,
    "NFMNMGAFIJI": 3498817376,
    "MBCOKNPMNFK": "Expectant",
    "icon": "UI_EmotionIcon28"
  },
  {
    "id": 2013,
    "IOCPLLBAMDH": 2,
    "CMCLFNNNLNL": 29,
    "NFMNMGAFIJI": 4197850024,
    "MBCOKNPMNFK": "Shocked",
    "icon": "UI_EmotionIcon29"
  },
  {
    "id": 2014,
    "IOCPLLBAMDH": 2,
    "CMCLFNNNLNL": 30,
    "NFMNMGAFIJI": 1034103432,
    "MBCOKNPMNFK": "I have an idea!",
    "icon": "UI_EmotionIcon30"
  },
  {
    "id": 2015,
    "IOCPLLBAMDH": 2,
    "CMCLFNNNLNL": 31,
    "NFMNMGAFIJI": 2398652032,
    "MBCOKNPMNFK": "Falling petals",
    "icon": "UI_EmotionIcon31"
  },
  {
    "id": 2016,
    "IOCPLLBAMDH": 2,
    "CMCLFNNNLNL": 32,
    "NFMNMGAFIJI": 2544833488,
    "MBCOKNPMNFK": "Applause",
    "icon": "UI_EmotionIcon32"
  },
  {
    "id": 3001,
    "IOCPLLBAMDH": 3,
    "CMCLFNNNLNL": 33,
    "NFMNMGAFIJI": 1534977544,
    "MBCOKNPMNFK": "Sipping tea",
    "icon": "UI_EmotionIcon33"
  },
  {
    "id": 3002,
    "IOCPLLBAMDH": 3,
    "CMCLFNNNLNL": 34,
    "NFMNMGAFIJI": 2555307640,
    "MBCOKNPMNFK": "I'll take them all",
    "icon": "UI_EmotionIcon34"
  },
  {
    "id": 3003,
    "IOCPLLBAMDH": 3,
    "CMCLFNNNLNL": 35,
    "NFMNMGAFIJI": 1632125688,
    "MBCOKNPMNFK": "Thinking",
    "icon": "UI_EmotionIcon35"
  },
  {
    "id": 3004,
    "IOCPLLBAMDH": 3,
    "CMCLFNNNLNL": 36,
    "NFMNMGAFIJI": 1131434688,
    "MBCOKNPMNFK": "Spread hands",
    "icon": "UI_EmotionIcon36"
  },
  {
    "id": 3005,
    "IOCPLLBAMDH": 3,
    "CMCLFNNNLNL": 37,
    "NFMNMGAFIJI": 2769474664,
    "MBCOKNPMNFK": "Sigh",
    "icon": "UI_EmotionIcon37"
  },
  {
    "id": 3006,
    "IOCPLLBAMDH": 3,
    "CMCLFNNNLNL": 38,
    "NFMNMGAFIJI": 2632615328,
    "MBCOKNPMNFK": "Pleased",
    "icon": "UI_EmotionIcon38"
  },
  {
    "id": 3007,
    "IOCPLLBAMDH": 3,
    "CMCLFNNNLNL": 39,
    "NFMNMGAFIJI": 1898858984,
    "MBCOKNPMNFK": "Irritable",
    "icon": "UI_EmotionIcon39"
  },
  {
    "id": 3008,
    "IOCPLLBAMDH": 3,
    "CMCLFNNNLNL": 40,
    "NFMNMGAFIJI": 3213744480,
    "MBCOKNPMNFK": "Bored",
    "icon": "UI_EmotionIcon40"
  },
  {
    "id": 3009,
    "IOCPLLBAMDH": 3,
    "CMCLFNNNLNL": 41,
    "NFMNMGAFIJI": 2001282080,
    "MBCOKNPMNFK": "Fearsome",
    "icon": "UI_EmotionIcon41"
  },
  {
    "id": 3010,
    "IOCPLLBAMDH": 3,
    "CMCLFNNNLNL": 42,
    "NFMNMGAFIJI": 1420623288,
    "MBCOKNPMNFK": "Proud",
    "icon": "UI_EmotionIcon42"
  },
  {
    "id": 3011,
    "IOCPLLBAMDH": 3,
    "CMCLFNNNLNL": 43,
    "NFMNMGAFIJI": 908574360,
    "MBCOKNPMNFK": "I'm heating up!",
    "icon": "UI_EmotionIcon43"
  },
  {
    "id": 3012,
    "IOCPLLBAMDH": 3,
    "CMCLFNNNLNL": 44,
    "NFMNMGAFIJI": 4172094872,
    "MBCOKNPMNFK": "So annoying!",
    "icon": "UI_EmotionIcon44"
  },
  {
    "id": 3013,
    "IOCPLLBAMDH": 3,
    "CMCLFNNNLNL": 45,
    "NFMNMGAFIJI": 1034683424,
    "MBCOKNPMNFK": "Mad",
    "icon": "UI_EmotionIcon45"
  },
  {
    "id": 3014,
    "IOCPLLBAMDH": 3,
    "CMCLFNNNLNL": 46,
    "NFMNMGAFIJI": 4105293048,
    "MBCOKNPMNFK": "I refuse.",
    "icon": "UI_EmotionIcon46"
  },
  {
    "id": 3015,
    "IOCPLLBAMDH": 3,
    "CMCLFNNNLNL": 47,
    "NFMNMGAFIJI": 3959088520,
    "MBCOKNPMNFK": "So hungry...",
    "icon": "UI_EmotionIcon47"
  },
  {
    "id": 3016,
    "IOCPLLBAMDH": 3,
    "CMCLFNNNLNL": 48,
    "NFMNMGAFIJI": 517895208,
    "MBCOKNPMNFK": "Mora!",
    "icon": "UI_EmotionIcon48"
  },
  {
    "id": 4001,
    "IOCPLLBAMDH": 4,
    "CMCLFNNNLNL": 49,
    "NFMNMGAFIJI": 2327427960,
    "MBCOKNPMNFK": "Have some flowers",
    "icon": "UI_EmotionIcon49"
  },
  {
    "id": 4002,
    "IOCPLLBAMDH": 4,
    "CMCLFNNNLNL": 50,
    "NFMNMGAFIJI": 944605128,
    "MBCOKNPMNFK": "It was nothing",
    "icon": "UI_EmotionIcon50"
  },
  {
    "id": 4003,
    "IOCPLLBAMDH": 4,
    "CMCLFNNNLNL": 51,
    "NFMNMGAFIJI": 148983184,
    "MBCOKNPMNFK": "What happened?",
    "icon": "UI_EmotionIcon51"
  },
  {
    "id": 4004,
    "IOCPLLBAMDH": 4,
    "CMCLFNNNLNL": 52,
    "NFMNMGAFIJI": 2504363040,
    "MBCOKNPMNFK": "Cold",
    "icon": "UI_EmotionIcon52"
  },
  {
    "id": 4005,
    "IOCPLLBAMDH": 4,
    "CMCLFNNNLNL": 53,
    "NFMNMGAFIJI": 2379081672,
    "MBCOKNPMNFK": "Snoozing",
    "icon": "UI_EmotionIcon53"
  },
  {
    "id": 4006,
    "IOCPLLBAMDH": 4,
    "CMCLFNNNLNL": 54,
    "NFMNMGAFIJI": 1737312080,
    "MBCOKNPMNFK": "No touching!",
    "icon": "UI_EmotionIcon54"
  },
  {
    "id": 4007,
    "IOCPLLBAMDH": 4,
    "CMCLFNNNLNL": 55,
    "NFMNMGAFIJI": 3318487864,
    "MBCOKNPMNFK": "Upset",
    "icon": "UI_EmotionIcon55"
  },
  {
    "id": 4008,
    "IOCPLLBAMDH": 4,
    "CMCLFNNNLNL": 56,
    "NFMNMGAFIJI": 3970019216,
    "MBCOKNPMNFK": "Not bad",
    "icon": "UI_EmotionIcon56"
  },
  {
    "id": 4009,
    "IOCPLLBAMDH": 4,
    "CMCLFNNNLNL": 57,
    "NFMNMGAFIJI": 224609936,
    "MBCOKNPMNFK": "Pray",
    "icon": "UI_EmotionIcon57"
  },
  {
    "id": 4010,
    "IOCPLLBAMDH": 4,
    "CMCLFNNNLNL": 58,
    "NFMNMGAFIJI": 1679266880,
    "MBCOKNPMNFK": "Good Morning",
    "icon": "UI_EmotionIcon58"
  },
  {
    "id": 4011,
    "IOCPLLBAMDH": 4,
    "CMCLFNNNLNL": 59,
    "NFMNMGAFIJI": 493602872,
    "MBCOKNPMNFK": "You can do it!",
    "icon": "UI_EmotionIcon59"
  },
  {
    "id": 4012,
    "IOCPLLBAMDH": 4,
    "CMCLFNNNLNL": 60,
    "NFMNMGAFIJI": 2624996048,
    "MBCOKNPMNFK": "Recording",
    "icon": "UI_EmotionIcon60"
  },
  {
    "id": 4013,
    "IOCPLLBAMDH": 4,
    "CMCLFNNNLNL": 61,
    "NFMNMGAFIJI": 4073711792,
    "MBCOKNPMNFK": "Shocked",
    "icon": "UI_EmotionIcon61"
  },
  {
    "id": 4014,
    "IOCPLLBAMDH": 4,
    "CMCLFNNNLNL": 62,
    "NFMNMGAFIJI": 1968453664,
    "MBCOKNPMNFK": "The light fades",
    "icon": "UI_EmotionIcon62"
  },
  {
    "id": 4015,
    "IOCPLLBAMDH": 4,
    "CMCLFNNNLNL": 63,
    "NFMNMGAFIJI": 2156516160,
    "MBCOKNPMNFK": "Not at all!",
    "icon": "UI_EmotionIcon63"
  },
  {
    "id": 4016,
    "IOCPLLBAMDH": 4,
    "CMCLFNNNLNL": 64,
    "NFMNMGAFIJI": 3343822376,
    "MBCOKNPMNFK": "Hahaha",
    "icon": "UI_EmotionIcon64"
  },
  {
    "id": 5001,
    "IOCPLLBAMDH": 5,
    "CMCLFNNNLNL": 65,
    "NFMNMGAFIJI": 3151258064,
    "MBCOKNPMNFK": "Evil laugh",
    "icon": "UI_EmotionIcon65"
  },
  {
    "id": 5002,
    "IOCPLLBAMDH": 5,
    "CMCLFNNNLNL": 66,
    "NFMNMGAFIJI": 399941720,
    "MBCOKNPMNFK": "Reciting poetry",
    "icon": "UI_EmotionIcon66"
  },
  {
    "id": 5003,
    "IOCPLLBAMDH": 5,
    "CMCLFNNNLNL": 67,
    "NFMNMGAFIJI": 133004912,
    "MBCOKNPMNFK": "Messed up",
    "icon": "UI_EmotionIcon67"
  },
  {
    "id": 5004,
    "IOCPLLBAMDH": 5,
    "CMCLFNNNLNL": 68,
    "NFMNMGAFIJI": 1716708504,
    "MBCOKNPMNFK": "Adorable",
    "icon": "UI_EmotionIcon68"
  },
  {
    "id": 5005,
    "IOCPLLBAMDH": 5,
    "CMCLFNNNLNL": 69,
    "NFMNMGAFIJI": 568938080,
    "MBCOKNPMNFK": "Frighten",
    "icon": "UI_EmotionIcon69"
  },
  {
    "id": 5006,
    "IOCPLLBAMDH": 5,
    "CMCLFNNNLNL": 70,
    "NFMNMGAFIJI": 395233512,
    "MBCOKNPMNFK": "I've got this!",
    "icon": "UI_EmotionIcon70"
  },
  {
    "id": 5007,
    "IOCPLLBAMDH": 5,
    "CMCLFNNNLNL": 71,
    "NFMNMGAFIJI": 3603469432,
    "MBCOKNPMNFK": "Yawn",
    "icon": "UI_EmotionIcon71"
  },
  {
    "id": 5008,
    "IOCPLLBAMDH": 5,
    "CMCLFNNNLNL": 72,
    "NFMNMGAFIJI": 3214558832,
    "MBCOKNPMNFK": "Pardon me",
    "icon": "UI_EmotionIcon72"
  },
  {
    "id": 5009,
    "IOCPLLBAMDH": 5,
    "CMCLFNNNLNL": 73,
    "NFMNMGAFIJI": 1343865712,
    "MBCOKNPMNFK": "Eating",
    "icon": "UI_EmotionIcon73"
  },
  {
    "id": 5010,
    "IOCPLLBAMDH": 5,
    "CMCLFNNNLNL": 74,
    "NFMNMGAFIJI": 1647892976,
    "MBCOKNPMNFK": "Rubs eyes",
    "icon": "UI_EmotionIcon74"
  },
  {
    "id": 5011,
    "IOCPLLBAMDH": 5,
    "CMCLFNNNLNL": 75,
    "NFMNMGAFIJI": 2867185600,
    "MBCOKNPMNFK": "Have a seat",
    "icon": "UI_EmotionIcon75"
  },
  {
    "id": 5012,
    "IOCPLLBAMDH": 5,
    "CMCLFNNNLNL": 76,
    "NFMNMGAFIJI": 1720911792,
    "MBCOKNPMNFK": "Bring it!",
    "icon": "UI_EmotionIcon76"
  },
  {
    "id": 5013,
    "IOCPLLBAMDH": 5,
    "CMCLFNNNLNL": 77,
    "NFMNMGAFIJI": 3589063928,
    "MBCOKNPMNFK": "Doubt",
    "icon": "UI_EmotionIcon77"
  },
  {
    "id": 5014,
    "IOCPLLBAMDH": 5,
    "CMCLFNNNLNL": 78,
    "NFMNMGAFIJI": 4262780768,
    "MBCOKNPMNFK": "Dazed",
    "icon": "UI_EmotionIcon78"
  },
  {
    "id": 5015,
    "IOCPLLBAMDH": 5,
    "CMCLFNNNLNL": 79,
    "NFMNMGAFIJI": 1168969472,
    "MBCOKNPMNFK": "Indifferent",
    "icon": "UI_EmotionIcon79"
  },
  {
    "id": 5016,
    "IOCPLLBAMDH": 5,
    "CMCLFNNNLNL": 80,
    "NFMNMGAFIJI": 1264282424,
    "MBCOKNPMNFK": "Frown",
    "icon": "UI_EmotionIcon80"
  },
  {
    "id": 6001,
    "IOCPLLBAMDH": 6,
    "CMCLFNNNLNL": 81,
    "NFMNMGAFIJI": 1700723928,
    "MBCOKNPMNFK": "Praise",
    "icon": "UI_EmotionIcon81"
  },
  {
    "id": 6002,
    "IOCPLLBAMDH": 6,
    "CMCLFNNNLNL": 82,
    "NFMNMGAFIJI": 3532920616,
    "MBCOKNPMNFK": "Let me see!",
    "icon": "UI_EmotionIcon82"
  },
  {
    "id": 6003,
    "IOCPLLBAMDH": 6,
    "CMCLFNNNLNL": 83,
    "NFMNMGAFIJI": 1990560928,
    "MBCOKNPMNFK": "Cheers!",
    "icon": "UI_EmotionIcon83"
  },
  {
    "id": 6004,
    "IOCPLLBAMDH": 6,
    "CMCLFNNNLNL": 84,
    "NFMNMGAFIJI": 347564536,
    "MBCOKNPMNFK": "Time to eat!",
    "icon": "UI_EmotionIcon84"
  },
  {
    "id": 6005,
    "IOCPLLBAMDH": 6,
    "CMCLFNNNLNL": 85,
    "NFMNMGAFIJI": 55422576,
    "MBCOKNPMNFK": "No problem",
    "icon": "UI_EmotionIcon85"
  },
  {
    "id": 6006,
    "IOCPLLBAMDH": 6,
    "CMCLFNNNLNL": 86,
    "NFMNMGAFIJI": 2694270952,
    "MBCOKNPMNFK": "I can't sleep",
    "icon": "UI_EmotionIcon86"
  },
  {
    "id": 6007,
    "IOCPLLBAMDH": 6,
    "CMCLFNNNLNL": 87,
    "NFMNMGAFIJI": 1684484784,
    "MBCOKNPMNFK": "What to do...",
    "icon": "UI_EmotionIcon87"
  },
  {
    "id": 6008,
    "IOCPLLBAMDH": 6,
    "CMCLFNNNLNL": 88,
    "NFMNMGAFIJI": 4071847752,
    "MBCOKNPMNFK": "Pleased",
    "icon": "UI_EmotionIcon88"
  },
  {
    "id": 6009,
    "IOCPLLBAMDH": 6,
    "CMCLFNNNLNL": 89,
    "NFMNMGAFIJI": 697416056,
    "MBCOKNPMNFK": "Perplexed",
    "icon": "UI_EmotionIcon89"
  },
  {
    "id": 6010,
    "IOCPLLBAMDH": 6,
    "CMCLFNNNLNL": 90,
    "NFMNMGAFIJI": 57786552,
    "MBCOKNPMNFK": "Rawr",
    "icon": "UI_EmotionIcon90"
  },
  {
    "id": 6011,
    "IOCPLLBAMDH": 6,
    "CMCLFNNNLNL": 91,
    "NFMNMGAFIJI": 3019535400,
    "MBCOKNPMNFK": "Confused",
    "icon": "UI_EmotionIcon91"
  },
  {
    "id": 6012,
    "IOCPLLBAMDH": 6,
    "CMCLFNNNLNL": 92,
    "NFMNMGAFIJI": 2087030192,
    "MBCOKNPMNFK": "Resting",
    "icon": "UI_EmotionIcon92"
  },
  {
    "id": 6013,
    "IOCPLLBAMDH": 6,
    "CMCLFNNNLNL": 93,
    "NFMNMGAFIJI": 2184922888,
    "MBCOKNPMNFK": "Dislike",
    "icon": "UI_EmotionIcon93"
  },
  {
    "id": 6014,
    "IOCPLLBAMDH": 6,
    "CMCLFNNNLNL": 94,
    "NFMNMGAFIJI": 375125688,
    "MBCOKNPMNFK": "Sweating",
    "icon": "UI_EmotionIcon94"
  },
  {
    "id": 6015,
    "IOCPLLBAMDH": 6,
    "CMCLFNNNLNL": 95,
    "NFMNMGAFIJI": 520787232,
    "MBCOKNPMNFK": "Stare",
    "icon": "UI_EmotionIcon95"
  },
  {
    "id": 6016,
    "IOCPLLBAMDH": 6,
    "CMCLFNNNLNL": 96,
    "NFMNMGAFIJI": 143815976,
    "MBCOKNPMNFK": "Clocking out",
    "icon": "UI_EmotionIcon96"
  },
  {
    "id": 7001,
    "IOCPLLBAMDH": 7,
    "CMCLFNNNLNL": 97,
    "NFMNMGAFIJI": 2629373360,
    "MBCOKNPMNFK": "Play With Me",
    "icon": "UI_EmotionIcon97"
  },
  {
    "id": 7002,
    "IOCPLLBAMDH": 7,
    "CMCLFNNNLNL": 98,
    "NFMNMGAFIJI": 3354975048,
    "MBCOKNPMNFK": "Pleeeease",
    "icon": "UI_EmotionIcon98"
  },
  {
    "id": 7003,
    "IOCPLLBAMDH": 7,
    "CMCLFNNNLNL": 99,
    "NFMNMGAFIJI": 3874458608,
    "MBCOKNPMNFK": "Nice!",
    "icon": "UI_EmotionIcon99"
  },
  {
    "id": 7004,
    "IOCPLLBAMDH": 7,
    "CMCLFNNNLNL": 100,
    "NFMNMGAFIJI": 1616186344,
    "MBCOKNPMNFK": "Shame",
    "icon": "UI_EmotionIcon100"
  },
  {
    "id": 7005,
    "IOCPLLBAMDH": 7,
    "CMCLFNNNLNL": 101,
    "NFMNMGAFIJI": 648311960,
    "MBCOKNPMNFK": "Hi",
    "icon": "UI_EmotionIcon101"
  },
  {
    "id": 7006,
    "IOCPLLBAMDH": 7,
    "CMCLFNNNLNL": 102,
    "NFMNMGAFIJI": 2489644960,
    "MBCOKNPMNFK": "Shock!",
    "icon": "UI_EmotionIcon102"
  },
  {
    "id": 7007,
    "IOCPLLBAMDH": 7,
    "CMCLFNNNLNL": 103,
    "NFMNMGAFIJI": 4212255792,
    "MBCOKNPMNFK": "Sweating",
    "icon": "UI_EmotionIcon103"
  },
  {
    "id": 7008,
    "IOCPLLBAMDH": 7,
    "CMCLFNNNLNL": 104,
    "NFMNMGAFIJI": 814979080,
    "MBCOKNPMNFK": "Small Smile",
    "icon": "UI_EmotionIcon104"
  },
  {
    "id": 7009,
    "IOCPLLBAMDH": 7,
    "CMCLFNNNLNL": 105,
    "NFMNMGAFIJI": 124049656,
    "MBCOKNPMNFK": "Are you alright?",
    "icon": "UI_EmotionIcon105"
  },
  {
    "id": 7010,
    "IOCPLLBAMDH": 7,
    "CMCLFNNNLNL": 106,
    "NFMNMGAFIJI": 963164016,
    "MBCOKNPMNFK": "Shy",
    "icon": "UI_EmotionIcon106"
  },
  {
    "id": 7011,
    "IOCPLLBAMDH": 7,
    "CMCLFNNNLNL": 107,
    "NFMNMGAFIJI": 280188648,
    "MBCOKNPMNFK": "Shh",
    "icon": "UI_EmotionIcon107"
  },
  {
    "id": 7012,
    "IOCPLLBAMDH": 7,
    "CMCLFNNNLNL": 108,
    "NFMNMGAFIJI": 2599804048,
    "MBCOKNPMNFK": "Panicked",
    "icon": "UI_EmotionIcon108"
  },
  {
    "id": 7013,
    "IOCPLLBAMDH": 7,
    "CMCLFNNNLNL": 109,
    "NFMNMGAFIJI": 746559936,
    "MBCOKNPMNFK": "Praise",
    "icon": "UI_EmotionIcon109"
  },
  {
    "id": 7014,
    "IOCPLLBAMDH": 7,
    "CMCLFNNNLNL": 110,
    "NFMNMGAFIJI": 511267504,
    "MBCOKNPMNFK": "Angry",
    "icon": "UI_EmotionIcon110"
  },
  {
    "id": 7015,
    "IOCPLLBAMDH": 7,
    "CMCLFNNNLNL": 111,
    "NFMNMGAFIJI": 14949640,
    "MBCOKNPMNFK": "Wry Smile",
    "icon": "UI_EmotionIcon111"
  },
  {
    "id": 7016,
    "IOCPLLBAMDH": 7,
    "CMCLFNNNLNL": 112,
    "NFMNMGAFIJI": 4114624504,
    "MBCOKNPMNFK": "Pensive",
    "icon": "UI_EmotionIcon112"
  },
  {
    "id": 8001,
    "IOCPLLBAMDH": 8,
    "CMCLFNNNLNL": 113,
    "NFMNMGAFIJI": 413711816,
    "MBCOKNPMNFK": "Small Smile",
    "icon": "UI_EmotionIcon113"
  },
  {
    "id": 8002,
    "IOCPLLBAMDH": 8,
    "CMCLFNNNLNL": 114,
    "NFMNMGAFIJI": 92585568,
    "MBCOKNPMNFK": "Sipping Tea",
    "icon": "UI_EmotionIcon114"
  },
  {
    "id": 8003,
    "IOCPLLBAMDH": 8,
    "CMCLFNNNLNL": 115,
    "NFMNMGAFIJI": 3129632496,
    "MBCOKNPMNFK": "Bow",
    "icon": "UI_EmotionIcon115"
  },
  {
    "id": 8004,
    "IOCPLLBAMDH": 8,
    "CMCLFNNNLNL": 116,
    "NFMNMGAFIJI": 1239986808,
    "MBCOKNPMNFK": "Good Morning",
    "icon": "UI_EmotionIcon116"
  },
  {
    "id": 8005,
    "IOCPLLBAMDH": 8,
    "CMCLFNNNLNL": 117,
    "NFMNMGAFIJI": 1932489064,
    "MBCOKNPMNFK": "No Problem",
    "icon": "UI_EmotionIcon117"
  },
  {
    "id": 8006,
    "IOCPLLBAMDH": 8,
    "CMCLFNNNLNL": 118,
    "NFMNMGAFIJI": 4081905112,
    "MBCOKNPMNFK": "Pleased",
    "icon": "UI_EmotionIcon118"
  },
  {
    "id": 8007,
    "IOCPLLBAMDH": 8,
    "CMCLFNNNLNL": 119,
    "NFMNMGAFIJI": 2368852320,
    "MBCOKNPMNFK": "Sorry",
    "icon": "UI_EmotionIcon119"
  },
  {
    "id": 8008,
    "IOCPLLBAMDH": 8,
    "CMCLFNNNLNL": 120,
    "NFMNMGAFIJI": 1658532504,
    "MBCOKNPMNFK": "Hey",
    "icon": "UI_EmotionIcon120"
  },
  {
    "id": 8009,
    "IOCPLLBAMDH": 8,
    "CMCLFNNNLNL": 121,
    "NFMNMGAFIJI": 735659944,
    "MBCOKNPMNFK": "Sleepy",
    "icon": "UI_EmotionIcon121"
  },
  {
    "id": 8010,
    "IOCPLLBAMDH": 8,
    "CMCLFNNNLNL": 122,
    "NFMNMGAFIJI": 3053117720,
    "MBCOKNPMNFK": "Angry",
    "icon": "UI_EmotionIcon122"
  },
  {
    "id": 8011,
    "IOCPLLBAMDH": 8,
    "CMCLFNNNLNL": 123,
    "NFMNMGAFIJI": 3074396640,
    "MBCOKNPMNFK": "Watch This",
    "icon": "UI_EmotionIcon123"
  },
  {
    "id": 8012,
    "IOCPLLBAMDH": 8,
    "CMCLFNNNLNL": 124,
    "NFMNMGAFIJI": 1270544536,
    "MBCOKNPMNFK": "Alert",
    "icon": "UI_EmotionIcon124"
  },
  {
    "id": 8013,
    "IOCPLLBAMDH": 8,
    "CMCLFNNNLNL": 125,
    "NFMNMGAFIJI": 488234720,
    "MBCOKNPMNFK": "Counting on You",
    "icon": "UI_EmotionIcon125"
  },
  {
    "id": 8014,
    "IOCPLLBAMDH": 8,
    "CMCLFNNNLNL": 126,
    "NFMNMGAFIJI": 1780079664,
    "MBCOKNPMNFK": "Awesome",
    "icon": "UI_EmotionIcon126"
  },
  {
    "id": 8015,
    "IOCPLLBAMDH": 8,
    "CMCLFNNNLNL": 127,
    "NFMNMGAFIJI": 1135266736,
    "MBCOKNPMNFK": "Hearty Laughter",
    "icon": "UI_EmotionIcon127"
  },
  {
    "id": 8016,
    "IOCPLLBAMDH": 8,
    "CMCLFNNNLNL": 128,
    "NFMNMGAFIJI": 1048443944,
    "MBCOKNPMNFK": "Bye",
    "icon": "UI_EmotionIcon128"
  },
  {
    "id": 9001,
    "IOCPLLBAMDH": 9,
    "CMCLFNNNLNL": 129,
    "NFMNMGAFIJI": 2636439536,
    "MBCOKNPMNFK": "Light Smile",
    "icon": "UI_EmotionIcon129"
  },
  {
    "id": 9002,
    "IOCPLLBAMDH": 9,
    "CMCLFNNNLNL": 130,
    "NFMNMGAFIJI": 2612534656,
    "MBCOKNPMNFK": "Surprise",
    "icon": "UI_EmotionIcon130"
  },
  {
    "id": 9003,
    "IOCPLLBAMDH": 9,
    "CMCLFNNNLNL": 131,
    "NFMNMGAFIJI": 3170344304,
    "MBCOKNPMNFK": "Tasty",
    "icon": "UI_EmotionIcon131"
  },
  {
    "id": 9004,
    "IOCPLLBAMDH": 9,
    "CMCLFNNNLNL": 132,
    "NFMNMGAFIJI": 4247596992,
    "MBCOKNPMNFK": "Threatening",
    "icon": "UI_EmotionIcon132"
  },
  {
    "id": 9005,
    "IOCPLLBAMDH": 9,
    "CMCLFNNNLNL": 133,
    "NFMNMGAFIJI": 2489211872,
    "MBCOKNPMNFK": "So Tired",
    "icon": "UI_EmotionIcon133"
  },
  {
    "id": 9006,
    "IOCPLLBAMDH": 9,
    "CMCLFNNNLNL": 134,
    "NFMNMGAFIJI": 3178947880,
    "MBCOKNPMNFK": "Laid-Back",
    "icon": "UI_EmotionIcon134"
  },
  {
    "id": 9007,
    "IOCPLLBAMDH": 9,
    "CMCLFNNNLNL": 135,
    "NFMNMGAFIJI": 1545551024,
    "MBCOKNPMNFK": "Fishing",
    "icon": "UI_EmotionIcon135"
  },
  {
    "id": 9008,
    "IOCPLLBAMDH": 9,
    "CMCLFNNNLNL": 136,
    "NFMNMGAFIJI": 3722320808,
    "MBCOKNPMNFK": "Pray",
    "icon": "UI_EmotionIcon136"
  },
  {
    "id": 9009,
    "IOCPLLBAMDH": 9,
    "CMCLFNNNLNL": 137,
    "NFMNMGAFIJI": 2037534504,
    "MBCOKNPMNFK": "Trying To Run?",
    "icon": "UI_EmotionIcon137"
  },
  {
    "id": 9010,
    "IOCPLLBAMDH": 9,
    "CMCLFNNNLNL": 138,
    "NFMNMGAFIJI": 2833178576,
    "MBCOKNPMNFK": "Happy",
    "icon": "UI_EmotionIcon138"
  },
  {
    "id": 9011,
    "IOCPLLBAMDH": 9,
    "CMCLFNNNLNL": 139,
    "NFMNMGAFIJI": 2874381304,
    "MBCOKNPMNFK": "I Refuse!",
    "icon": "UI_EmotionIcon139"
  },
  {
    "id": 9012,
    "IOCPLLBAMDH": 9,
    "CMCLFNNNLNL": 140,
    "NFMNMGAFIJI": 216751848,
    "MBCOKNPMNFK": "Forward!",
    "icon": "UI_EmotionIcon140"
  },
  {
    "id": 9013,
    "IOCPLLBAMDH": 9,
    "CMCLFNNNLNL": 141,
    "NFMNMGAFIJI": 2702579256,
    "MBCOKNPMNFK": "Doubt",
    "icon": "UI_EmotionIcon141"
  },
  {
    "id": 9014,
    "IOCPLLBAMDH": 9,
    "CMCLFNNNLNL": 142,
    "NFMNMGAFIJI": 1455904384,
    "MBCOKNPMNFK": "Congrats!",
    "icon": "UI_EmotionIcon142"
  },
  {
    "id": 9015,
    "IOCPLLBAMDH": 9,
    "CMCLFNNNLNL": 143,
    "NFMNMGAFIJI": 3540672392,
    "MBCOKNPMNFK": "Starry-Eyed",
    "icon": "UI_EmotionIcon143"
  },
  {
    "id": 9016,
    "IOCPLLBAMDH": 9,
    "CMCLFNNNLNL": 144,
    "NFMNMGAFIJI": 2302672664,
    "MBCOKNPMNFK": "Ehehe~",
    "icon": "UI_EmotionIcon144"
  },
  {
    "id": 10001,
    "IOCPLLBAMDH": 10,
    "CMCLFNNNLNL": 145,
    "NFMNMGAFIJI": 4254252360,
    "MBCOKNPMNFK": "Peek",
    "icon": "UI_EmotionIcon145"
  },
  {
    "id": 10002,
    "IOCPLLBAMDH": 10,
    "CMCLFNNNLNL": 146,
    "NFMNMGAFIJI": 246246312,
    "MBCOKNPMNFK": "Darn!",
    "icon": "UI_EmotionIcon146"
  },
  {
    "id": 10003,
    "IOCPLLBAMDH": 10,
    "CMCLFNNNLNL": 147,
    "NFMNMGAFIJI": 1236780064,
    "MBCOKNPMNFK": "Surfing",
    "icon": "UI_EmotionIcon147"
  },
  {
    "id": 10004,
    "IOCPLLBAMDH": 10,
    "CMCLFNNNLNL": 148,
    "NFMNMGAFIJI": 3090395200,
    "MBCOKNPMNFK": "Perplexed",
    "icon": "UI_EmotionIcon148"
  },
  {
    "id": 10005,
    "IOCPLLBAMDH": 10,
    "CMCLFNNNLNL": 149,
    "NFMNMGAFIJI": 356332048,
    "MBCOKNPMNFK": "Shocked",
    "icon": "UI_EmotionIcon149"
  },
  {
    "id": 10006,
    "IOCPLLBAMDH": 10,
    "CMCLFNNNLNL": 150,
    "NFMNMGAFIJI": 4082606776,
    "MBCOKNPMNFK": "Greetings",
    "icon": "UI_EmotionIcon150"
  },
  {
    "id": 10007,
    "IOCPLLBAMDH": 10,
    "CMCLFNNNLNL": 151,
    "NFMNMGAFIJI": 24511552,
    "MBCOKNPMNFK": "Love",
    "icon": "UI_EmotionIcon151"
  },
  {
    "id": 10008,
    "IOCPLLBAMDH": 10,
    "CMCLFNNNLNL": 152,
    "NFMNMGAFIJI": 3921034408,
    "MBCOKNPMNFK": "Stomachache",
    "icon": "UI_EmotionIcon152"
  },
  {
    "id": 10009,
    "IOCPLLBAMDH": 10,
    "CMCLFNNNLNL": 153,
    "NFMNMGAFIJI": 3232358048,
    "MBCOKNPMNFK": "Frightened",
    "icon": "UI_EmotionIcon153"
  },
  {
    "id": 10010,
    "IOCPLLBAMDH": 10,
    "CMCLFNNNLNL": 154,
    "NFMNMGAFIJI": 3397704040,
    "MBCOKNPMNFK": "Hold Up High",
    "icon": "UI_EmotionIcon154"
  },
  {
    "id": 10011,
    "IOCPLLBAMDH": 10,
    "CMCLFNNNLNL": 155,
    "NFMNMGAFIJI": 133058392,
    "MBCOKNPMNFK": "Eyes on Me!",
    "icon": "UI_EmotionIcon155"
  },
  {
    "id": 10012,
    "IOCPLLBAMDH": 10,
    "CMCLFNNNLNL": 156,
    "NFMNMGAFIJI": 2658538968,
    "MBCOKNPMNFK": "Charge!",
    "icon": "UI_EmotionIcon156"
  },
  {
    "id": 10013,
    "IOCPLLBAMDH": 10,
    "CMCLFNNNLNL": 157,
    "NFMNMGAFIJI": 3447817928,
    "MBCOKNPMNFK": "Reluctant",
    "icon": "UI_EmotionIcon157"
  },
  {
    "id": 10014,
    "IOCPLLBAMDH": 10,
    "CMCLFNNNLNL": 158,
    "NFMNMGAFIJI": 4030490944,
    "MBCOKNPMNFK": "High Five!",
    "icon": "UI_EmotionIcon158"
  },
  {
    "id": 10015,
    "IOCPLLBAMDH": 10,
    "CMCLFNNNLNL": 159,
    "NFMNMGAFIJI": 2978679960,
    "MBCOKNPMNFK": "Lying Flat",
    "icon": "UI_EmotionIcon159"
  },
  {
    "id": 10016,
    "IOCPLLBAMDH": 10,
    "CMCLFNNNLNL": 160,
    "NFMNMGAFIJI": 1011654168,
    "MBCOKNPMNFK": "Thinking",
    "icon": "UI_EmotionIcon160"
  },
  {
    "id": 11001,
    "IOCPLLBAMDH": 11,
    "CMCLFNNNLNL": 161,
    "NFMNMGAFIJI": 900188400,
    "MBCOKNPMNFK": "Taunt",
    "icon": "UI_EmotionIcon161"
  },
  {
    "id": 11002,
    "IOCPLLBAMDH": 11,
    "CMCLFNNNLNL": 162,
    "NFMNMGAFIJI": 3493182568,
    "MBCOKNPMNFK": "Hearty Laughter",
    "icon": "UI_EmotionIcon162"
  },
  {
    "id": 11003,
    "IOCPLLBAMDH": 11,
    "CMCLFNNNLNL": 163,
    "NFMNMGAFIJI": 4036034800,
    "MBCOKNPMNFK": "Perplexed",
    "icon": "UI_EmotionIcon163"
  },
  {
    "id": 11004,
    "IOCPLLBAMDH": 11,
    "CMCLFNNNLNL": 164,
    "NFMNMGAFIJI": 2340555048,
    "MBCOKNPMNFK": "Eating Sweets",
    "icon": "UI_EmotionIcon164"
  },
  {
    "id": 11005,
    "IOCPLLBAMDH": 11,
    "CMCLFNNNLNL": 165,
    "NFMNMGAFIJI": 769399976,
    "MBCOKNPMNFK": "Grin",
    "icon": "UI_EmotionIcon165"
  },
  {
    "id": 11006,
    "IOCPLLBAMDH": 11,
    "CMCLFNNNLNL": 166,
    "NFMNMGAFIJI": 1317881016,
    "MBCOKNPMNFK": "Cry",
    "icon": "UI_EmotionIcon166"
  },
  {
    "id": 11007,
    "IOCPLLBAMDH": 11,
    "CMCLFNNNLNL": 167,
    "NFMNMGAFIJI": 163778080,
    "MBCOKNPMNFK": "Happy",
    "icon": "UI_EmotionIcon167"
  },
  {
    "id": 11008,
    "IOCPLLBAMDH": 11,
    "CMCLFNNNLNL": 168,
    "NFMNMGAFIJI": 1147955104,
    "MBCOKNPMNFK": "Starry-Eyed",
    "icon": "UI_EmotionIcon168"
  },
  {
    "id": 11009,
    "IOCPLLBAMDH": 11,
    "CMCLFNNNLNL": 169,
    "NFMNMGAFIJI": 2651227424,
    "MBCOKNPMNFK": "Evil Laugh",
    "icon": "UI_EmotionIcon169"
  },
  {
    "id": 11010,
    "IOCPLLBAMDH": 11,
    "CMCLFNNNLNL": 170,
    "NFMNMGAFIJI": 1042779152,
    "MBCOKNPMNFK": "Pensive",
    "icon": "UI_EmotionIcon170"
  },
  {
    "id": 11011,
    "IOCPLLBAMDH": 11,
    "CMCLFNNNLNL": 171,
    "NFMNMGAFIJI": 3517667384,
    "MBCOKNPMNFK": "Leave it to Me",
    "icon": "UI_EmotionIcon171"
  },
  {
    "id": 11012,
    "IOCPLLBAMDH": 11,
    "CMCLFNNNLNL": 172,
    "NFMNMGAFIJI": 4041539480,
    "MBCOKNPMNFK": "Invite",
    "icon": "UI_EmotionIcon172"
  },
  {
    "id": 11013,
    "IOCPLLBAMDH": 11,
    "CMCLFNNNLNL": 173,
    "NFMNMGAFIJI": 588899144,
    "MBCOKNPMNFK": "Sneeze",
    "icon": "UI_EmotionIcon173"
  },
  {
    "id": 11014,
    "IOCPLLBAMDH": 11,
    "CMCLFNNNLNL": 174,
    "NFMNMGAFIJI": 859880024,
    "MBCOKNPMNFK": "Dislike",
    "icon": "UI_EmotionIcon174"
  },
  {
    "id": 11015,
    "IOCPLLBAMDH": 11,
    "CMCLFNNNLNL": 175,
    "NFMNMGAFIJI": 3708391112,
    "MBCOKNPMNFK": "Splendorous",
    "icon": "UI_EmotionIcon175"
  },
  {
    "id": 11016,
    "IOCPLLBAMDH": 11,
    "CMCLFNNNLNL": 176,
    "NFMNMGAFIJI": 1917385696,
    "MBCOKNPMNFK": "Examining",
    "icon": "UI_EmotionIcon176"
  },
  {
    "id": 12001,
    "IOCPLLBAMDH": 12,
    "CMCLFNNNLNL": 177,
    "NFMNMGAFIJI": 2947060472,
    "MBCOKNPMNFK": "Doubtful",
    "icon": "UI_EmotionIcon177"
  },
  {
    "id": 12002,
    "IOCPLLBAMDH": 12,
    "CMCLFNNNLNL": 178,
    "NFMNMGAFIJI": 3838154408,
    "MBCOKNPMNFK": "Speechless",
    "icon": "UI_EmotionIcon178"
  },
  {
    "id": 12003,
    "IOCPLLBAMDH": 12,
    "CMCLFNNNLNL": 179,
    "NFMNMGAFIJI": 579520648,
    "MBCOKNPMNFK": "Sipping Tea",
    "icon": "UI_EmotionIcon179"
  },
  {
    "id": 12004,
    "IOCPLLBAMDH": 12,
    "CMCLFNNNLNL": 180,
    "NFMNMGAFIJI": 977042728,
    "MBCOKNPMNFK": "Stare",
    "icon": "UI_EmotionIcon180"
  },
  {
    "id": 12005,
    "IOCPLLBAMDH": 12,
    "CMCLFNNNLNL": 181,
    "NFMNMGAFIJI": 2886705960,
    "MBCOKNPMNFK": "WINK",
    "icon": "UI_EmotionIcon181"
  },
  {
    "id": 12006,
    "IOCPLLBAMDH": 12,
    "CMCLFNNNLNL": 182,
    "NFMNMGAFIJI": 1228516568,
    "MBCOKNPMNFK": "Small Smile",
    "icon": "UI_EmotionIcon182"
  },
  {
    "id": 12007,
    "IOCPLLBAMDH": 12,
    "CMCLFNNNLNL": 183,
    "NFMNMGAFIJI": 1444106760,
    "MBCOKNPMNFK": "Shock!",
    "icon": "UI_EmotionIcon183"
  },
  {
    "id": 12008,
    "IOCPLLBAMDH": 12,
    "CMCLFNNNLNL": 184,
    "NFMNMGAFIJI": 987809880,
    "MBCOKNPMNFK": "Expectant",
    "icon": "UI_EmotionIcon184"
  },
  {
    "id": 12009,
    "IOCPLLBAMDH": 12,
    "CMCLFNNNLNL": 185,
    "NFMNMGAFIJI": 1899914088,
    "MBCOKNPMNFK": "Impregnable",
    "icon": "UI_EmotionIcon185"
  },
  {
    "id": 12010,
    "IOCPLLBAMDH": 12,
    "CMCLFNNNLNL": 186,
    "NFMNMGAFIJI": 3561662008,
    "MBCOKNPMNFK": "Consternation",
    "icon": "UI_EmotionIcon186"
  },
  {
    "id": 12011,
    "IOCPLLBAMDH": 12,
    "CMCLFNNNLNL": 187,
    "NFMNMGAFIJI": 84246976,
    "MBCOKNPMNFK": "A Toast!",
    "icon": "UI_EmotionIcon187"
  },
  {
    "id": 12012,
    "IOCPLLBAMDH": 12,
    "CMCLFNNNLNL": 188,
    "NFMNMGAFIJI": 562712112,
    "MBCOKNPMNFK": "Confident",
    "icon": "UI_EmotionIcon188"
  },
  {
    "id": 12013,
    "IOCPLLBAMDH": 12,
    "CMCLFNNNLNL": 189,
    "NFMNMGAFIJI": 2902396160,
    "MBCOKNPMNFK": "Disbelieving",
    "icon": "UI_EmotionIcon189"
  },
  {
    "id": 12014,
    "IOCPLLBAMDH": 12,
    "CMCLFNNNLNL": 190,
    "NFMNMGAFIJI": 1596925616,
    "MBCOKNPMNFK": "Eat Snow",
    "icon": "UI_EmotionIcon190"
  },
  {
    "id": 12015,
    "IOCPLLBAMDH": 12,
    "CMCLFNNNLNL": 191,
    "NFMNMGAFIJI": 3993370992,
    "MBCOKNPMNFK": "Rolling",
    "icon": "UI_EmotionIcon191"
  },
  {
    "id": 12016,
    "IOCPLLBAMDH": 12,
    "CMCLFNNNLNL": 192,
    "NFMNMGAFIJI": 2974582360,
    "MBCOKNPMNFK": "You can do it!",
    "icon": "UI_EmotionIcon192"
  },
  {
    "id": 13001,
    "IOCPLLBAMDH": 13,
    "CMCLFNNNLNL": 193,
    "NFMNMGAFIJI": 3639286824,
    "MBCOKNPMNFK": "Hahaha!",
    "icon": "UI_EmotionIcon193"
  },
  {
    "id": 13002,
    "IOCPLLBAMDH": 13,
    "CMCLFNNNLNL": 194,
    "NFMNMGAFIJI": 593419136,
    "MBCOKNPMNFK": "Chilling",
    "icon": "UI_EmotionIcon194"
  },
  {
    "id": 13003,
    "IOCPLLBAMDH": 13,
    "CMCLFNNNLNL": 195,
    "NFMNMGAFIJI": 861599344,
    "MBCOKNPMNFK": "Fruit Juice",
    "icon": "UI_EmotionIcon195"
  },
  {
    "id": 13004,
    "IOCPLLBAMDH": 13,
    "CMCLFNNNLNL": 196,
    "NFMNMGAFIJI": 1454338520,
    "MBCOKNPMNFK": "Approval",
    "icon": "UI_EmotionIcon196"
  },
  {
    "id": 13005,
    "IOCPLLBAMDH": 13,
    "CMCLFNNNLNL": 197,
    "NFMNMGAFIJI": 3918022000,
    "MBCOKNPMNFK": "Drinks Tea",
    "icon": "UI_EmotionIcon197"
  },
  {
    "id": 13006,
    "IOCPLLBAMDH": 13,
    "CMCLFNNNLNL": 198,
    "NFMNMGAFIJI": 3487258248,
    "MBCOKNPMNFK": "Give That Back",
    "icon": "UI_EmotionIcon198"
  },
  {
    "id": 13007,
    "IOCPLLBAMDH": 13,
    "CMCLFNNNLNL": 199,
    "NFMNMGAFIJI": 2827552392,
    "MBCOKNPMNFK": "Charging Up",
    "icon": "UI_EmotionIcon199"
  },
  {
    "id": 13008,
    "IOCPLLBAMDH": 13,
    "CMCLFNNNLNL": 200,
    "NFMNMGAFIJI": 1181532600,
    "MBCOKNPMNFK": "Low Charge",
    "icon": "UI_EmotionIcon200"
  },
  {
    "id": 13009,
    "IOCPLLBAMDH": 13,
    "CMCLFNNNLNL": 201,
    "NFMNMGAFIJI": 283999032,
    "MBCOKNPMNFK": "Mocking Smile",
    "icon": "UI_EmotionIcon201"
  },
  {
    "id": 13010,
    "IOCPLLBAMDH": 13,
    "CMCLFNNNLNL": 202,
    "NFMNMGAFIJI": 2442079816,
    "MBCOKNPMNFK": "Obfuscating",
    "icon": "UI_EmotionIcon202"
  },
  {
    "id": 13011,
    "IOCPLLBAMDH": 13,
    "CMCLFNNNLNL": 203,
    "NFMNMGAFIJI": 3735279488,
    "MBCOKNPMNFK": "Work in Progress",
    "icon": "UI_EmotionIcon203"
  },
  {
    "id": 13012,
    "IOCPLLBAMDH": 13,
    "CMCLFNNNLNL": 204,
    "NFMNMGAFIJI": 2418171952,
    "MBCOKNPMNFK": "Evil Smile",
    "icon": "UI_EmotionIcon204"
  },
  {
    "id": 13013,
    "IOCPLLBAMDH": 13,
    "CMCLFNNNLNL": 205,
    "NFMNMGAFIJI": 4063017840,
    "MBCOKNPMNFK": "My Thanks",
    "icon": "UI_EmotionIcon205"
  },
  {
    "id": 13014,
    "IOCPLLBAMDH": 13,
    "CMCLFNNNLNL": 206,
    "NFMNMGAFIJI": 2908498544,
    "MBCOKNPMNFK": "Prepare Yourself",
    "icon": "UI_EmotionIcon206"
  },
  {
    "id": 13015,
    "IOCPLLBAMDH": 13,
    "CMCLFNNNLNL": 207,
    "NFMNMGAFIJI": 3843657192,
    "MBCOKNPMNFK": "Mulling It Over",
    "icon": "UI_EmotionIcon207"
  },
  {
    "id": 13016,
    "IOCPLLBAMDH": 13,
    "CMCLFNNNLNL": 208,
    "NFMNMGAFIJI": 3216075672,
    "MBCOKNPMNFK": "Shut-In",
    "icon": "UI_EmotionIcon208"
  },
  {
    "id": 14001,
    "IOCPLLBAMDH": 14,
    "CMCLFNNNLNL": 209,
    "NFMNMGAFIJI": 2541660920,
    "MBCOKNPMNFK": "Drinking Milk Tea",
    "icon": "UI_EmotionIcon209"
  },
  {
    "id": 14002,
    "IOCPLLBAMDH": 14,
    "CMCLFNNNLNL": 210,
    "NFMNMGAFIJI": 4183290880,
    "MBCOKNPMNFK": "Thinking",
    "icon": "UI_EmotionIcon210"
  },
  {
    "id": 14003,
    "IOCPLLBAMDH": 14,
    "CMCLFNNNLNL": 211,
    "NFMNMGAFIJI": 403037272,
    "MBCOKNPMNFK": "Now Working",
    "icon": "UI_EmotionIcon211"
  },
  {
    "id": 14004,
    "IOCPLLBAMDH": 14,
    "CMCLFNNNLNL": 212,
    "NFMNMGAFIJI": 2600512984,
    "MBCOKNPMNFK": "Suspicious",
    "icon": "UI_EmotionIcon212"
  },
  {
    "id": 14005,
    "IOCPLLBAMDH": 14,
    "CMCLFNNNLNL": 213,
    "NFMNMGAFIJI": 2153003768,
    "MBCOKNPMNFK": "Training",
    "icon": "UI_EmotionIcon213"
  },
  {
    "id": 14006,
    "IOCPLLBAMDH": 14,
    "CMCLFNNNLNL": 214,
    "NFMNMGAFIJI": 208685672,
    "MBCOKNPMNFK": "Greed",
    "icon": "UI_EmotionIcon214"
  },
  {
    "id": 14007,
    "IOCPLLBAMDH": 14,
    "CMCLFNNNLNL": 215,
    "NFMNMGAFIJI": 1822388424,
    "MBCOKNPMNFK": "Dazed",
    "icon": "UI_EmotionIcon215"
  },
  {
    "id": 14008,
    "IOCPLLBAMDH": 14,
    "CMCLFNNNLNL": 216,
    "NFMNMGAFIJI": 3105971992,
    "MBCOKNPMNFK": "Bashful",
    "icon": "UI_EmotionIcon216"
  },
  {
    "id": 14009,
    "IOCPLLBAMDH": 14,
    "CMCLFNNNLNL": 217,
    "NFMNMGAFIJI": 2483024480,
    "MBCOKNPMNFK": "Sleepy Time",
    "icon": "UI_EmotionIcon217"
  },
  {
    "id": 14010,
    "IOCPLLBAMDH": 14,
    "CMCLFNNNLNL": 218,
    "NFMNMGAFIJI": 2649673656,
    "MBCOKNPMNFK": "Sighing",
    "icon": "UI_EmotionIcon218"
  },
  {
    "id": 14011,
    "IOCPLLBAMDH": 14,
    "CMCLFNNNLNL": 219,
    "NFMNMGAFIJI": 3829378624,
    "MBCOKNPMNFK": "Relaxed",
    "icon": "UI_EmotionIcon219"
  },
  {
    "id": 14012,
    "IOCPLLBAMDH": 14,
    "CMCLFNNNLNL": 220,
    "NFMNMGAFIJI": 3326391096,
    "MBCOKNPMNFK": "Ehe~",
    "icon": "UI_EmotionIcon220"
  },
  {
    "id": 14013,
    "IOCPLLBAMDH": 14,
    "CMCLFNNNLNL": 221,
    "NFMNMGAFIJI": 409611424,
    "MBCOKNPMNFK": "I've Got an Idea!",
    "icon": "UI_EmotionIcon221"
  },
  {
    "id": 14014,
    "IOCPLLBAMDH": 14,
    "CMCLFNNNLNL": 222,
    "NFMNMGAFIJI": 742606712,
    "MBCOKNPMNFK": "Too Much Stress",
    "icon": "UI_EmotionIcon222"
  },
  {
    "id": 14015,
    "IOCPLLBAMDH": 14,
    "CMCLFNNNLNL": 223,
    "NFMNMGAFIJI": 3389638808,
    "MBCOKNPMNFK": "Focused",
    "icon": "UI_EmotionIcon223"
  },
  {
    "id": 14016,
    "IOCPLLBAMDH": 14,
    "CMCLFNNNLNL": 224,
    "NFMNMGAFIJI": 3564728944,
    "MBCOKNPMNFK": "Making Sure",
    "icon": "UI_EmotionIcon224"
  },
  {
    "id": 15001,
    "IOCPLLBAMDH": 15,
    "CMCLFNNNLNL": 225,
    "NFMNMGAFIJI": 2712114944,
    "MBCOKNPMNFK": "Cold Laugh",
    "icon": "UI_EmotionIcon225"
  },
  {
    "id": 15002,
    "IOCPLLBAMDH": 15,
    "CMCLFNNNLNL": 226,
    "NFMNMGAFIJI": 1782227888,
    "MBCOKNPMNFK": "Drinks Tea",
    "icon": "UI_EmotionIcon226"
  },
  {
    "id": 15003,
    "IOCPLLBAMDH": 15,
    "CMCLFNNNLNL": 227,
    "NFMNMGAFIJI": 505007680,
    "MBCOKNPMNFK": "Threatening",
    "icon": "UI_EmotionIcon227"
  },
  {
    "id": 15004,
    "IOCPLLBAMDH": 15,
    "CMCLFNNNLNL": 228,
    "NFMNMGAFIJI": 1340808984,
    "MBCOKNPMNFK": "Nap Time",
    "icon": "UI_EmotionIcon228"
  },
  {
    "id": 15005,
    "IOCPLLBAMDH": 15,
    "CMCLFNNNLNL": 229,
    "NFMNMGAFIJI": 1675264936,
    "MBCOKNPMNFK": "Pleased",
    "icon": "UI_EmotionIcon229"
  },
  {
    "id": 15006,
    "IOCPLLBAMDH": 15,
    "CMCLFNNNLNL": 230,
    "NFMNMGAFIJI": 302475760,
    "MBCOKNPMNFK": "Challenge",
    "icon": "UI_EmotionIcon230"
  },
  {
    "id": 15007,
    "IOCPLLBAMDH": 15,
    "CMCLFNNNLNL": 231,
    "NFMNMGAFIJI": 3170184080,
    "MBCOKNPMNFK": "Lend a Hand",
    "icon": "UI_EmotionIcon231"
  },
  {
    "id": 15008,
    "IOCPLLBAMDH": 15,
    "CMCLFNNNLNL": 232,
    "NFMNMGAFIJI": 3660011992,
    "MBCOKNPMNFK": "Agh!",
    "icon": "UI_EmotionIcon232"
  },
  {
    "id": 15009,
    "IOCPLLBAMDH": 15,
    "CMCLFNNNLNL": 233,
    "NFMNMGAFIJI": 2179655368,
    "MBCOKNPMNFK": "Panic",
    "icon": "UI_EmotionIcon233"
  },
  {
    "id": 15010,
    "IOCPLLBAMDH": 15,
    "CMCLFNNNLNL": 234,
    "NFMNMGAFIJI": 3829449744,
    "MBCOKNPMNFK": "Rage",
    "icon": "UI_EmotionIcon234"
  },
  {
    "id": 15011,
    "IOCPLLBAMDH": 15,
    "CMCLFNNNLNL": 235,
    "NFMNMGAFIJI": 1016532432,
    "MBCOKNPMNFK": "Sure Pass",
    "icon": "UI_EmotionIcon235"
  },
  {
    "id": 15012,
    "IOCPLLBAMDH": 15,
    "CMCLFNNNLNL": 236,
    "NFMNMGAFIJI": 3275783144,
    "MBCOKNPMNFK": "Ready for Battle",
    "icon": "UI_EmotionIcon236"
  },
  {
    "id": 15013,
    "IOCPLLBAMDH": 15,
    "CMCLFNNNLNL": 237,
    "NFMNMGAFIJI": 878082592,
    "MBCOKNPMNFK": "Show Up",
    "icon": "UI_EmotionIcon237"
  },
  {
    "id": 15014,
    "IOCPLLBAMDH": 15,
    "CMCLFNNNLNL": 238,
    "NFMNMGAFIJI": 2953658824,
    "MBCOKNPMNFK": "Doubt",
    "icon": "UI_EmotionIcon238"
  },
  {
    "id": 15015,
    "IOCPLLBAMDH": 15,
    "CMCLFNNNLNL": 239,
    "NFMNMGAFIJI": 2119603960,
    "MBCOKNPMNFK": "Warning",
    "icon": "UI_EmotionIcon239"
  },
  {
    "id": 15016,
    "IOCPLLBAMDH": 15,
    "CMCLFNNNLNL": 240,
    "NFMNMGAFIJI": 2037398448,
    "MBCOKNPMNFK": "Objection!",
    "icon": "UI_EmotionIcon240"
  },
  {
    "id": 16001,
    "IOCPLLBAMDH": 16,
    "CMCLFNNNLNL": 241,
    "NFMNMGAFIJI": 1858335136,
    "MBCOKNPMNFK": "I'm the Best!",
    "icon": "UI_EmotionIcon241"
  },
  {
    "id": 16002,
    "IOCPLLBAMDH": 16,
    "CMCLFNNNLNL": 242,
    "NFMNMGAFIJI": 3076566840,
    "MBCOKNPMNFK": "Sigh",
    "icon": "UI_EmotionIcon242"
  },
  {
    "id": 16003,
    "IOCPLLBAMDH": 16,
    "CMCLFNNNLNL": 243,
    "NFMNMGAFIJI": 2867324592,
    "MBCOKNPMNFK": "Noticed",
    "icon": "UI_EmotionIcon243"
  },
  {
    "id": 16004,
    "IOCPLLBAMDH": 16,
    "CMCLFNNNLNL": 244,
    "NFMNMGAFIJI": 2144943520,
    "MBCOKNPMNFK": "Punch!",
    "icon": "UI_EmotionIcon244"
  },
  {
    "id": 16005,
    "IOCPLLBAMDH": 16,
    "CMCLFNNNLNL": 245,
    "NFMNMGAFIJI": 1217990832,
    "MBCOKNPMNFK": "You Can Do It!",
    "icon": "UI_EmotionIcon245"
  },
  {
    "id": 16006,
    "IOCPLLBAMDH": 16,
    "CMCLFNNNLNL": 246,
    "NFMNMGAFIJI": 3739122624,
    "MBCOKNPMNFK": "Crystals Please",
    "icon": "UI_EmotionIcon246"
  },
  {
    "id": 16007,
    "IOCPLLBAMDH": 16,
    "CMCLFNNNLNL": 247,
    "NFMNMGAFIJI": 3723460864,
    "MBCOKNPMNFK": "Satisfaction",
    "icon": "UI_EmotionIcon247"
  },
  {
    "id": 16008,
    "IOCPLLBAMDH": 16,
    "CMCLFNNNLNL": 248,
    "NFMNMGAFIJI": 180969344,
    "MBCOKNPMNFK": "Allow Me!",
    "icon": "UI_EmotionIcon248"
  },
  {
    "id": 16009,
    "IOCPLLBAMDH": 16,
    "CMCLFNNNLNL": 249,
    "NFMNMGAFIJI": 3165871136,
    "MBCOKNPMNFK": "Strokes Chin",
    "icon": "UI_EmotionIcon249"
  },
  {
    "id": 16010,
    "IOCPLLBAMDH": 16,
    "CMCLFNNNLNL": 250,
    "NFMNMGAFIJI": 3891799088,
    "MBCOKNPMNFK": "Stretch",
    "icon": "UI_EmotionIcon250"
  },
  {
    "id": 16011,
    "IOCPLLBAMDH": 16,
    "CMCLFNNNLNL": 251,
    "NFMNMGAFIJI": 2349847552,
    "MBCOKNPMNFK": "So Hot",
    "icon": "UI_EmotionIcon251"
  },
  {
    "id": 16012,
    "IOCPLLBAMDH": 16,
    "CMCLFNNNLNL": 252,
    "NFMNMGAFIJI": 3046606824,
    "MBCOKNPMNFK": "Let's Try",
    "icon": "UI_EmotionIcon252"
  },
  {
    "id": 16013,
    "IOCPLLBAMDH": 16,
    "CMCLFNNNLNL": 253,
    "NFMNMGAFIJI": 3721236256,
    "MBCOKNPMNFK": "Dazed",
    "icon": "UI_EmotionIcon253"
  },
  {
    "id": 16014,
    "IOCPLLBAMDH": 16,
    "CMCLFNNNLNL": 254,
    "NFMNMGAFIJI": 133044408,
    "MBCOKNPMNFK": "Disappointment",
    "icon": "UI_EmotionIcon254"
  },
  {
    "id": 16015,
    "IOCPLLBAMDH": 16,
    "CMCLFNNNLNL": 255,
    "NFMNMGAFIJI": 2680205360,
    "MBCOKNPMNFK": "Stay Calm",
    "icon": "UI_EmotionIcon255"
  },
  {
    "id": 16016,
    "IOCPLLBAMDH": 16,
    "CMCLFNNNLNL": 256,
    "NFMNMGAFIJI": 3905468104,
    "MBCOKNPMNFK": "On Vacation",
    "icon": "UI_EmotionIcon256"
  },
  {
    "id": 17001,
    "IOCPLLBAMDH": 17,
    "CMCLFNNNLNL": 257,
    "NFMNMGAFIJI": 805697008,
    "MBCOKNPMNFK": "Taps Blackboard",
    "icon": "UI_EmotionIcon257"
  },
  {
    "id": 17002,
    "IOCPLLBAMDH": 17,
    "CMCLFNNNLNL": 258,
    "NFMNMGAFIJI": 2350891256,
    "MBCOKNPMNFK": "Pats",
    "icon": "UI_EmotionIcon258"
  },
  {
    "id": 17003,
    "IOCPLLBAMDH": 17,
    "CMCLFNNNLNL": 259,
    "NFMNMGAFIJI": 2728083584,
    "MBCOKNPMNFK": "Shock",
    "icon": "UI_EmotionIcon259"
  },
  {
    "id": 17004,
    "IOCPLLBAMDH": 17,
    "CMCLFNNNLNL": 260,
    "NFMNMGAFIJI": 3615665256,
    "MBCOKNPMNFK": "Observing",
    "icon": "UI_EmotionIcon260"
  },
  {
    "id": 17005,
    "IOCPLLBAMDH": 17,
    "CMCLFNNNLNL": 261,
    "NFMNMGAFIJI": 1932745008,
    "MBCOKNPMNFK": "Yearning",
    "icon": "UI_EmotionIcon261"
  },
  {
    "id": 17006,
    "IOCPLLBAMDH": 17,
    "CMCLFNNNLNL": 262,
    "NFMNMGAFIJI": 2236480304,
    "MBCOKNPMNFK": "Embarrassed",
    "icon": "UI_EmotionIcon262"
  },
  {
    "id": 17007,
    "IOCPLLBAMDH": 17,
    "CMCLFNNNLNL": 263,
    "NFMNMGAFIJI": 2461621624,
    "MBCOKNPMNFK": "Lesson Time",
    "icon": "UI_EmotionIcon263"
  },
  {
    "id": 17008,
    "IOCPLLBAMDH": 17,
    "CMCLFNNNLNL": 264,
    "NFMNMGAFIJI": 4293444328,
    "MBCOKNPMNFK": "Alert",
    "icon": "UI_EmotionIcon264"
  },
  {
    "id": 17009,
    "IOCPLLBAMDH": 17,
    "CMCLFNNNLNL": 265,
    "NFMNMGAFIJI": 299130736,
    "MBCOKNPMNFK": "Sales Pitch",
    "icon": "UI_EmotionIcon265"
  },
  {
    "id": 17010,
    "IOCPLLBAMDH": 17,
    "CMCLFNNNLNL": 266,
    "NFMNMGAFIJI": 3339245616,
    "MBCOKNPMNFK": "Evil Grin",
    "icon": "UI_EmotionIcon266"
  },
  {
    "id": 17011,
    "IOCPLLBAMDH": 17,
    "CMCLFNNNLNL": 267,
    "NFMNMGAFIJI": 689955872,
    "MBCOKNPMNFK": "Search",
    "icon": "UI_EmotionIcon267"
  },
  {
    "id": 17012,
    "IOCPLLBAMDH": 17,
    "CMCLFNNNLNL": 268,
    "NFMNMGAFIJI": 4059278288,
    "MBCOKNPMNFK": "Dreaming of Mora",
    "icon": "UI_EmotionIcon268"
  },
  {
    "id": 17013,
    "IOCPLLBAMDH": 17,
    "CMCLFNNNLNL": 269,
    "NFMNMGAFIJI": 3649790488,
    "MBCOKNPMNFK": "Help Me!",
    "icon": "UI_EmotionIcon269"
  },
  {
    "id": 17014,
    "IOCPLLBAMDH": 17,
    "CMCLFNNNLNL": 270,
    "NFMNMGAFIJI": 4185986248,
    "MBCOKNPMNFK": "Let's Scoot!",
    "icon": "UI_EmotionIcon270"
  },
  {
    "id": 17015,
    "IOCPLLBAMDH": 17,
    "CMCLFNNNLNL": 271,
    "NFMNMGAFIJI": 1338676504,
    "MBCOKNPMNFK": "Dreaming",
    "icon": "UI_EmotionIcon271"
  },
  {
    "id": 17016,
    "IOCPLLBAMDH": 17,
    "CMCLFNNNLNL": 272,
    "NFMNMGAFIJI": 3555612944,
    "MBCOKNPMNFK": "Disguised",
    "icon": "UI_EmotionIcon272"
  },
  {
    "id": 18001,
    "IOCPLLBAMDH": 18,
    "CMCLFNNNLNL": 273,
    "NFMNMGAFIJI": 2010752760,
    "MBCOKNPMNFK": "Duel!",
    "icon": "UI_EmotionIcon273"
  },
  {
    "id": 18002,
    "IOCPLLBAMDH": 18,
    "CMCLFNNNLNL": 274,
    "NFMNMGAFIJI": 4039952280,
    "MBCOKNPMNFK": "Judgment!",
    "icon": "UI_EmotionIcon274"
  },
  {
    "id": 18003,
    "IOCPLLBAMDH": 18,
    "CMCLFNNNLNL": 275,
    "NFMNMGAFIJI": 3713494208,
    "MBCOKNPMNFK": "I'm Here",
    "icon": "UI_EmotionIcon275"
  },
  {
    "id": 18004,
    "IOCPLLBAMDH": 18,
    "CMCLFNNNLNL": 276,
    "NFMNMGAFIJI": 3983001896,
    "MBCOKNPMNFK": "Sweating",
    "icon": "UI_EmotionIcon276"
  },
  {
    "id": 18005,
    "IOCPLLBAMDH": 18,
    "CMCLFNNNLNL": 277,
    "NFMNMGAFIJI": 3598891296,
    "MBCOKNPMNFK": "Awkward",
    "icon": "UI_EmotionIcon277"
  },
  {
    "id": 18006,
    "IOCPLLBAMDH": 18,
    "CMCLFNNNLNL": 278,
    "NFMNMGAFIJI": 3480518472,
    "MBCOKNPMNFK": "Now Thinking",
    "icon": "UI_EmotionIcon278"
  },
  {
    "id": 18007,
    "IOCPLLBAMDH": 18,
    "CMCLFNNNLNL": 279,
    "NFMNMGAFIJI": 1559447640,
    "MBCOKNPMNFK": "Emerge",
    "icon": "UI_EmotionIcon279"
  },
  {
    "id": 18008,
    "IOCPLLBAMDH": 18,
    "CMCLFNNNLNL": 280,
    "NFMNMGAFIJI": 1012690976,
    "MBCOKNPMNFK": "That's All, Folks",
    "icon": "UI_EmotionIcon280"
  },
  {
    "id": 18009,
    "IOCPLLBAMDH": 18,
    "CMCLFNNNLNL": 281,
    "NFMNMGAFIJI": 2018668336,
    "MBCOKNPMNFK": "I'll Protect You",
    "icon": "UI_EmotionIcon281"
  },
  {
    "id": 18010,
    "IOCPLLBAMDH": 18,
    "CMCLFNNNLNL": 282,
    "NFMNMGAFIJI": 1606849536,
    "MBCOKNPMNFK": "Happy Birthday",
    "icon": "UI_EmotionIcon282"
  },
  {
    "id": 18011,
    "IOCPLLBAMDH": 18,
    "CMCLFNNNLNL": 283,
    "NFMNMGAFIJI": 3667949232,
    "MBCOKNPMNFK": "Thanks!",
    "icon": "UI_EmotionIcon283"
  },
  {
    "id": 18012,
    "IOCPLLBAMDH": 18,
    "CMCLFNNNLNL": 284,
    "NFMNMGAFIJI": 3489269848,
    "MBCOKNPMNFK": "Praying",
    "icon": "UI_EmotionIcon284"
  },
  {
    "id": 18013,
    "IOCPLLBAMDH": 18,
    "CMCLFNNNLNL": 285,
    "NFMNMGAFIJI": 3398620160,
    "MBCOKNPMNFK": "Silly Grin",
    "icon": "UI_EmotionIcon285"
  },
  {
    "id": 18014,
    "IOCPLLBAMDH": 18,
    "CMCLFNNNLNL": 286,
    "NFMNMGAFIJI": 3444128632,
    "MBCOKNPMNFK": "Awoo!",
    "icon": "UI_EmotionIcon286"
  },
  {
    "id": 18015,
    "IOCPLLBAMDH": 18,
    "CMCLFNNNLNL": 287,
    "NFMNMGAFIJI": 3031654880,
    "MBCOKNPMNFK": "Hunting",
    "icon": "UI_EmotionIcon287"
  },
  {
    "id": 18016,
    "IOCPLLBAMDH": 18,
    "CMCLFNNNLNL": 288,
    "NFMNMGAFIJI": 2952252008,
    "MBCOKNPMNFK": "Overwhelmed",
    "icon": "UI_EmotionIcon288"
  },
  {
    "id": 19001,
    "IOCPLLBAMDH": 19,
    "CMCLFNNNLNL": 289,
    "NFMNMGAFIJI": 3791097416,
    "MBCOKNPMNFK": "Curious",
    "icon": "UI_EmotionIcon289"
  },
  {
    "id": 19002,
    "IOCPLLBAMDH": 19,
    "CMCLFNNNLNL": 290,
    "NFMNMGAFIJI": 2398325208,
    "MBCOKNPMNFK": "Happy",
    "icon": "UI_EmotionIcon290"
  },
  {
    "id": 19003,
    "IOCPLLBAMDH": 19,
    "CMCLFNNNLNL": 291,
    "NFMNMGAFIJI": 2164454136,
    "MBCOKNPMNFK": "Deep Thought",
    "icon": "UI_EmotionIcon291"
  },
  {
    "id": 19004,
    "IOCPLLBAMDH": 19,
    "CMCLFNNNLNL": 292,
    "NFMNMGAFIJI": 3466573072,
    "MBCOKNPMNFK": "Great!",
    "icon": "UI_EmotionIcon292"
  },
  {
    "id": 19005,
    "IOCPLLBAMDH": 19,
    "CMCLFNNNLNL": 293,
    "NFMNMGAFIJI": 3011227688,
    "MBCOKNPMNFK": "Excited",
    "icon": "UI_EmotionIcon293"
  },
  {
    "id": 19006,
    "IOCPLLBAMDH": 19,
    "CMCLFNNNLNL": 294,
    "NFMNMGAFIJI": 3073202720,
    "MBCOKNPMNFK": "Lunch Break",
    "icon": "UI_EmotionIcon294"
  },
  {
    "id": 19007,
    "IOCPLLBAMDH": 19,
    "CMCLFNNNLNL": 295,
    "NFMNMGAFIJI": 3331765120,
    "MBCOKNPMNFK": "*cries in poverty*",
    "icon": "UI_EmotionIcon295"
  },
  {
    "id": 19008,
    "IOCPLLBAMDH": 19,
    "CMCLFNNNLNL": 296,
    "NFMNMGAFIJI": 1447763864,
    "MBCOKNPMNFK": "Sleepwalk",
    "icon": "UI_EmotionIcon296"
  },
  {
    "id": 19009,
    "IOCPLLBAMDH": 19,
    "CMCLFNNNLNL": 297,
    "NFMNMGAFIJI": 4236190752,
    "MBCOKNPMNFK": "Zero Progress",
    "icon": "UI_EmotionIcon297"
  },
  {
    "id": 19010,
    "IOCPLLBAMDH": 19,
    "CMCLFNNNLNL": 298,
    "NFMNMGAFIJI": 233892704,
    "MBCOKNPMNFK": "Mozzie Swat",
    "icon": "UI_EmotionIcon298"
  },
  {
    "id": 19011,
    "IOCPLLBAMDH": 19,
    "CMCLFNNNLNL": 299,
    "NFMNMGAFIJI": 625077656,
    "MBCOKNPMNFK": "Cry",
    "icon": "UI_EmotionIcon299"
  },
  {
    "id": 19012,
    "IOCPLLBAMDH": 19,
    "CMCLFNNNLNL": 300,
    "NFMNMGAFIJI": 1940757736,
    "MBCOKNPMNFK": "Fly!",
    "icon": "UI_EmotionIcon300"
  },
  {
    "id": 19013,
    "IOCPLLBAMDH": 19,
    "CMCLFNNNLNL": 301,
    "NFMNMGAFIJI": 2914281008,
    "MBCOKNPMNFK": "There, There",
    "icon": "UI_EmotionIcon301"
  },
  {
    "id": 19014,
    "IOCPLLBAMDH": 19,
    "CMCLFNNNLNL": 302,
    "NFMNMGAFIJI": 3695491120,
    "MBCOKNPMNFK": "Scared",
    "icon": "UI_EmotionIcon302"
  },
  {
    "id": 19015,
    "IOCPLLBAMDH": 19,
    "CMCLFNNNLNL": 303,
    "NFMNMGAFIJI": 64799168,
    "MBCOKNPMNFK": "Dazed",
    "icon": "UI_EmotionIcon303"
  },
  {
    "id": 19016,
    "IOCPLLBAMDH": 19,
    "CMCLFNNNLNL": 304,
    "NFMNMGAFIJI": 3676195672,
    "MBCOKNPMNFK": "Go Go!",
    "icon": "UI_EmotionIcon304"
  },
  {
    "id": 20001,
    "IOCPLLBAMDH": 20,
    "CMCLFNNNLNL": 305,
    "NFMNMGAFIJI": 296337192,
    "MBCOKNPMNFK": "Greetings",
    "icon": "UI_EmotionIcon305"
  },
  {
    "id": 20002,
    "IOCPLLBAMDH": 20,
    "CMCLFNNNLNL": 306,
    "NFMNMGAFIJI": 3255022720,
    "MBCOKNPMNFK": "Sobs",
    "icon": "UI_EmotionIcon306"
  },
  {
    "id": 20003,
    "IOCPLLBAMDH": 20,
    "CMCLFNNNLNL": 307,
    "NFMNMGAFIJI": 3128275448,
    "MBCOKNPMNFK": "Funny Face",
    "icon": "UI_EmotionIcon307"
  },
  {
    "id": 20004,
    "IOCPLLBAMDH": 20,
    "CMCLFNNNLNL": 308,
    "NFMNMGAFIJI": 3991915496,
    "MBCOKNPMNFK": "Collapsed",
    "icon": "UI_EmotionIcon308"
  },
  {
    "id": 20005,
    "IOCPLLBAMDH": 20,
    "CMCLFNNNLNL": 309,
    "NFMNMGAFIJI": 281493304,
    "MBCOKNPMNFK": "Thinking",
    "icon": "UI_EmotionIcon309"
  },
  {
    "id": 20006,
    "IOCPLLBAMDH": 20,
    "CMCLFNNNLNL": 310,
    "NFMNMGAFIJI": 2942842664,
    "MBCOKNPMNFK": "Blush",
    "icon": "UI_EmotionIcon310"
  },
  {
    "id": 20007,
    "IOCPLLBAMDH": 20,
    "CMCLFNNNLNL": 311,
    "NFMNMGAFIJI": 1018152080,
    "MBCOKNPMNFK": "Welcome!",
    "icon": "UI_EmotionIcon311"
  },
  {
    "id": 20008,
    "IOCPLLBAMDH": 20,
    "CMCLFNNNLNL": 312,
    "NFMNMGAFIJI": 3521903360,
    "MBCOKNPMNFK": "Come Again?",
    "icon": "UI_EmotionIcon312"
  },
  {
    "id": 20009,
    "IOCPLLBAMDH": 20,
    "CMCLFNNNLNL": 313,
    "NFMNMGAFIJI": 2858985272,
    "MBCOKNPMNFK": "Invite",
    "icon": "UI_EmotionIcon313"
  },
  {
    "id": 20010,
    "IOCPLLBAMDH": 20,
    "CMCLFNNNLNL": 314,
    "NFMNMGAFIJI": 1686035824,
    "MBCOKNPMNFK": "Victory",
    "icon": "UI_EmotionIcon314"
  },
  {
    "id": 20011,
    "IOCPLLBAMDH": 20,
    "CMCLFNNNLNL": 315,
    "NFMNMGAFIJI": 828747160,
    "MBCOKNPMNFK": "Not Bad!",
    "icon": "UI_EmotionIcon315"
  },
  {
    "id": 20012,
    "IOCPLLBAMDH": 20,
    "CMCLFNNNLNL": 316,
    "NFMNMGAFIJI": 2403086080,
    "MBCOKNPMNFK": "Another Round!",
    "icon": "UI_EmotionIcon316"
  },
  {
    "id": 20013,
    "IOCPLLBAMDH": 20,
    "CMCLFNNNLNL": 317,
    "NFMNMGAFIJI": 2537266336,
    "MBCOKNPMNFK": "Confident",
    "icon": "UI_EmotionIcon317"
  },
  {
    "id": 20014,
    "IOCPLLBAMDH": 20,
    "CMCLFNNNLNL": 318,
    "NFMNMGAFIJI": 1280021584,
    "MBCOKNPMNFK": "How Did That Happen",
    "icon": "UI_EmotionIcon318"
  },
  {
    "id": 20015,
    "IOCPLLBAMDH": 20,
    "CMCLFNNNLNL": 319,
    "NFMNMGAFIJI": 197412024,
    "MBCOKNPMNFK": "I've Learned a Lot",
    "icon": "UI_EmotionIcon319"
  },
  {
    "id": 20016,
    "IOCPLLBAMDH": 20,
    "CMCLFNNNLNL": 320,
    "NFMNMGAFIJI": 1023394048,
    "MBCOKNPMNFK": "Lucky!",
    "icon": "UI_EmotionIcon320"
  },
  {
    "id": 21001,
    "IOCPLLBAMDH": 21,
    "CMCLFNNNLNL": 321,
    "NFMNMGAFIJI": 3394734520,
    "MBCOKNPMNFK": "Happy Holidays!",
    "icon": "UI_EmotionIcon321"
  },
  {
    "id": 21002,
    "IOCPLLBAMDH": 21,
    "CMCLFNNNLNL": 322,
    "NFMNMGAFIJI": 3296340696,
    "MBCOKNPMNFK": "Good Job!",
    "icon": "UI_EmotionIcon322"
  },
  {
    "id": 21003,
    "IOCPLLBAMDH": 21,
    "CMCLFNNNLNL": 323,
    "NFMNMGAFIJI": 2400823848,
    "MBCOKNPMNFK": "I'm Done",
    "icon": "UI_EmotionIcon323"
  },
  {
    "id": 21004,
    "IOCPLLBAMDH": 21,
    "CMCLFNNNLNL": 324,
    "NFMNMGAFIJI": 1975915448,
    "MBCOKNPMNFK": "Greed",
    "icon": "UI_EmotionIcon324"
  },
  {
    "id": 21005,
    "IOCPLLBAMDH": 21,
    "CMCLFNNNLNL": 325,
    "NFMNMGAFIJI": 3081619592,
    "MBCOKNPMNFK": "Bon Voyage!",
    "icon": "UI_EmotionIcon325"
  },
  {
    "id": 21006,
    "IOCPLLBAMDH": 21,
    "CMCLFNNNLNL": 326,
    "NFMNMGAFIJI": 1573858616,
    "MBCOKNPMNFK": "Double Happiness",
    "icon": "UI_EmotionIcon326"
  },
  {
    "id": 21007,
    "IOCPLLBAMDH": 21,
    "CMCLFNNNLNL": 327,
    "NFMNMGAFIJI": 1086044808,
    "MBCOKNPMNFK": "Joyful Reunion",
    "icon": "UI_EmotionIcon327"
  },
  {
    "id": 21008,
    "IOCPLLBAMDH": 21,
    "CMCLFNNNLNL": 328,
    "NFMNMGAFIJI": 1113355832,
    "MBCOKNPMNFK": "Good Fortune",
    "icon": "UI_EmotionIcon328"
  },
  {
    "id": 21009,
    "IOCPLLBAMDH": 21,
    "CMCLFNNNLNL": 329,
    "NFMNMGAFIJI": 4068010264,
    "MBCOKNPMNFK": "Thanks, Boss!",
    "icon": "UI_EmotionIcon329"
  },
  {
    "id": 21010,
    "IOCPLLBAMDH": 21,
    "CMCLFNNNLNL": 330,
    "NFMNMGAFIJI": 2245454200,
    "MBCOKNPMNFK": "Plentiful Mora",
    "icon": "UI_EmotionIcon330"
  },
  {
    "id": 21011,
    "IOCPLLBAMDH": 21,
    "CMCLFNNNLNL": 331,
    "NFMNMGAFIJI": 811518520,
    "MBCOKNPMNFK": "Great Fortune",
    "icon": "UI_EmotionIcon331"
  },
  {
    "id": 21012,
    "IOCPLLBAMDH": 21,
    "CMCLFNNNLNL": 332,
    "NFMNMGAFIJI": 2745125360,
    "MBCOKNPMNFK": "Always Happy",
    "icon": "UI_EmotionIcon332"
  },
  {
    "id": 21013,
    "IOCPLLBAMDH": 21,
    "CMCLFNNNLNL": 333,
    "NFMNMGAFIJI": 2495369616,
    "MBCOKNPMNFK": "Use Your Brain",
    "icon": "UI_EmotionIcon333"
  },
  {
    "id": 21014,
    "IOCPLLBAMDH": 21,
    "CMCLFNNNLNL": 334,
    "NFMNMGAFIJI": 2967751672,
    "MBCOKNPMNFK": "Clock Out",
    "icon": "UI_EmotionIcon334"
  },
  {
    "id": 21015,
    "IOCPLLBAMDH": 21,
    "CMCLFNNNLNL": 335,
    "NFMNMGAFIJI": 2700675320,
    "MBCOKNPMNFK": "So Noisy",
    "icon": "UI_EmotionIcon335"
  },
  {
    "id": 21016,
    "IOCPLLBAMDH": 21,
    "CMCLFNNNLNL": 336,
    "NFMNMGAFIJI": 3131664896,
    "MBCOKNPMNFK": "Undisturbed",
    "icon": "UI_EmotionIcon336"
  },
  {
    "id": 22001,
    "IOCPLLBAMDH": 22,
    "CMCLFNNNLNL": 337,
    "NFMNMGAFIJI": 507052584,
    "MBCOKNPMNFK": "Got it",
    "icon": "UI_EmotionIcon337"
  },
  {
    "id": 22002,
    "IOCPLLBAMDH": 22,
    "CMCLFNNNLNL": 338,
    "NFMNMGAFIJI": 1111842216,
    "MBCOKNPMNFK": "Nervous",
    "icon": "UI_EmotionIcon338"
  },
  {
    "id": 22003,
    "IOCPLLBAMDH": 22,
    "CMCLFNNNLNL": 339,
    "NFMNMGAFIJI": 2018940584,
    "MBCOKNPMNFK": "Take this!",
    "icon": "UI_EmotionIcon339"
  },
  {
    "id": 22004,
    "IOCPLLBAMDH": 22,
    "CMCLFNNNLNL": 340,
    "NFMNMGAFIJI": 2260191488,
    "MBCOKNPMNFK": "Have some flowers",
    "icon": "UI_EmotionIcon340"
  },
  {
    "id": 22005,
    "IOCPLLBAMDH": 22,
    "CMCLFNNNLNL": 341,
    "NFMNMGAFIJI": 3664016408,
    "MBCOKNPMNFK": "Sigh",
    "icon": "UI_EmotionIcon341"
  },
  {
    "id": 22006,
    "IOCPLLBAMDH": 22,
    "CMCLFNNNLNL": 342,
    "NFMNMGAFIJI": 4147095056,
    "MBCOKNPMNFK": "So scary",
    "icon": "UI_EmotionIcon342"
  },
  {
    "id": 22007,
    "IOCPLLBAMDH": 22,
    "CMCLFNNNLNL": 343,
    "NFMNMGAFIJI": 3834998256,
    "MBCOKNPMNFK": "I'm here!",
    "icon": "UI_EmotionIcon343"
  },
  {
    "id": 22008,
    "IOCPLLBAMDH": 22,
    "CMCLFNNNLNL": 344,
    "NFMNMGAFIJI": 1268237248,
    "MBCOKNPMNFK": "Yay",
    "icon": "UI_EmotionIcon344"
  },
  {
    "id": 22009,
    "IOCPLLBAMDH": 22,
    "CMCLFNNNLNL": 345,
    "NFMNMGAFIJI": 2842727200,
    "MBCOKNPMNFK": "No? Not funny?",
    "icon": "UI_EmotionIcon345"
  },
  {
    "id": 22010,
    "IOCPLLBAMDH": 22,
    "CMCLFNNNLNL": 346,
    "NFMNMGAFIJI": 1914680128,
    "MBCOKNPMNFK": "Inspection!",
    "icon": "UI_EmotionIcon346"
  },
  {
    "id": 22011,
    "IOCPLLBAMDH": 22,
    "CMCLFNNNLNL": 347,
    "NFMNMGAFIJI": 3825389456,
    "MBCOKNPMNFK": "Hopeless",
    "icon": "UI_EmotionIcon347"
  },
  {
    "id": 22012,
    "IOCPLLBAMDH": 22,
    "CMCLFNNNLNL": 348,
    "NFMNMGAFIJI": 1310589008,
    "MBCOKNPMNFK": "Flop",
    "icon": "UI_EmotionIcon348"
  },
  {
    "id": 22013,
    "IOCPLLBAMDH": 22,
    "CMCLFNNNLNL": 349,
    "NFMNMGAFIJI": 2630777328,
    "MBCOKNPMNFK": "No response",
    "icon": "UI_EmotionIcon349"
  },
  {
    "id": 22014,
    "IOCPLLBAMDH": 22,
    "CMCLFNNNLNL": 350,
    "NFMNMGAFIJI": 2656782336,
    "MBCOKNPMNFK": "Stretch",
    "icon": "UI_EmotionIcon350"
  },
  {
    "id": 22015,
    "IOCPLLBAMDH": 22,
    "CMCLFNNNLNL": 351,
    "NFMNMGAFIJI": 1651018840,
    "MBCOKNPMNFK": "Sorry to disturb",
    "icon": "UI_EmotionIcon351"
  },
  {
    "id": 22016,
    "IOCPLLBAMDH": 22,
    "CMCLFNNNLNL": 352,
    "NFMNMGAFIJI": 1568898112,
    "MBCOKNPMNFK": "Envious",
    "icon": "UI_EmotionIcon352"
  },
  {
    "id": 23001,
    "IOCPLLBAMDH": 23,
    "CMCLFNNNLNL": 353,
    "NFMNMGAFIJI": 487758992,
    "MBCOKNPMNFK": "Concerned",
    "icon": "UI_EmotionIcon353"
  },
  {
    "id": 23002,
    "IOCPLLBAMDH": 23,
    "CMCLFNNNLNL": 354,
    "NFMNMGAFIJI": 1141264344,
    "MBCOKNPMNFK": "Gloom",
    "icon": "UI_EmotionIcon354"
  },
  {
    "id": 23003,
    "IOCPLLBAMDH": 23,
    "CMCLFNNNLNL": 355,
    "NFMNMGAFIJI": 2588114456,
    "MBCOKNPMNFK": "Vomiting Blood",
    "icon": "UI_EmotionIcon355"
  },
  {
    "id": 23004,
    "IOCPLLBAMDH": 23,
    "CMCLFNNNLNL": 356,
    "NFMNMGAFIJI": 3832860024,
    "MBCOKNPMNFK": "Taking Medicine",
    "icon": "UI_EmotionIcon356"
  },
  {
    "id": 23005,
    "IOCPLLBAMDH": 23,
    "CMCLFNNNLNL": 357,
    "NFMNMGAFIJI": 3285884536,
    "MBCOKNPMNFK": "Now I'm Angry",
    "icon": "UI_EmotionIcon357"
  },
  {
    "id": 23006,
    "IOCPLLBAMDH": 23,
    "CMCLFNNNLNL": 358,
    "NFMNMGAFIJI": 611443864,
    "MBCOKNPMNFK": "Help Me!",
    "icon": "UI_EmotionIcon358"
  },
  {
    "id": 23007,
    "IOCPLLBAMDH": 23,
    "CMCLFNNNLNL": 359,
    "NFMNMGAFIJI": 4070343256,
    "MBCOKNPMNFK": "Time for Work!",
    "icon": "UI_EmotionIcon359"
  },
  {
    "id": 23008,
    "IOCPLLBAMDH": 23,
    "CMCLFNNNLNL": 360,
    "NFMNMGAFIJI": 1517944952,
    "MBCOKNPMNFK": "Accepting Orders",
    "icon": "UI_EmotionIcon360"
  },
  {
    "id": 23009,
    "IOCPLLBAMDH": 23,
    "CMCLFNNNLNL": 361,
    "NFMNMGAFIJI": 2450953536,
    "MBCOKNPMNFK": "Wink Wink",
    "icon": "UI_EmotionIcon361"
  },
  {
    "id": 23010,
    "IOCPLLBAMDH": 23,
    "CMCLFNNNLNL": 362,
    "NFMNMGAFIJI": 524568816,
    "MBCOKNPMNFK": "Giving Comments",
    "icon": "UI_EmotionIcon362"
  },
  {
    "id": 23011,
    "IOCPLLBAMDH": 23,
    "CMCLFNNNLNL": 363,
    "NFMNMGAFIJI": 3975356824,
    "MBCOKNPMNFK": "I'll Take It From Here",
    "icon": "UI_EmotionIcon363"
  },
  {
    "id": 23012,
    "IOCPLLBAMDH": 23,
    "CMCLFNNNLNL": 364,
    "NFMNMGAFIJI": 986447432,
    "MBCOKNPMNFK": "You Can Do This!",
    "icon": "UI_EmotionIcon364"
  },
  {
    "id": 23013,
    "IOCPLLBAMDH": 23,
    "CMCLFNNNLNL": 365,
    "NFMNMGAFIJI": 3875767104,
    "MBCOKNPMNFK": "Zoned Out",
    "icon": "UI_EmotionIcon365"
  },
  {
    "id": 23014,
    "IOCPLLBAMDH": 23,
    "CMCLFNNNLNL": 366,
    "NFMNMGAFIJI": 3085534520,
    "MBCOKNPMNFK": "Watch Me!",
    "icon": "UI_EmotionIcon366"
  },
  {
    "id": 23015,
    "IOCPLLBAMDH": 23,
    "CMCLFNNNLNL": 367,
    "NFMNMGAFIJI": 3236914424,
    "MBCOKNPMNFK": "Have at You!",
    "icon": "UI_EmotionIcon367"
  },
  {
    "id": 23016,
    "IOCPLLBAMDH": 23,
    "CMCLFNNNLNL": 368,
    "NFMNMGAFIJI": 3805896792,
    "MBCOKNPMNFK": "You're Invited",
    "icon": "UI_EmotionIcon368"
  },
  {
    "id": 24001,
    "IOCPLLBAMDH": 24,
    "CMCLFNNNLNL": 369,
    "NFMNMGAFIJI": 1810260952,
    "MBCOKNPMNFK": "Five Star Rating, Purr-ease~",
    "icon": "UI_EmotionIcon369"
  },
  {
    "id": 24002,
    "IOCPLLBAMDH": 24,
    "CMCLFNNNLNL": 370,
    "NFMNMGAFIJI": 3671934928,
    "MBCOKNPMNFK": "Please Take It",
    "icon": "UI_EmotionIcon370"
  },
  {
    "id": 24003,
    "IOCPLLBAMDH": 24,
    "CMCLFNNNLNL": 371,
    "NFMNMGAFIJI": 404350840,
    "MBCOKNPMNFK": "Right Away!",
    "icon": "UI_EmotionIcon371"
  },
  {
    "id": 24004,
    "IOCPLLBAMDH": 24,
    "CMCLFNNNLNL": 372,
    "NFMNMGAFIJI": 944602664,
    "MBCOKNPMNFK": "I'm Serious!",
    "icon": "UI_EmotionIcon372"
  },
  {
    "id": 24005,
    "IOCPLLBAMDH": 24,
    "CMCLFNNNLNL": 373,
    "NFMNMGAFIJI": 177525720,
    "MBCOKNPMNFK": "Perplexed",
    "icon": "UI_EmotionIcon373"
  },
  {
    "id": 24006,
    "IOCPLLBAMDH": 24,
    "CMCLFNNNLNL": 374,
    "NFMNMGAFIJI": 3227392320,
    "MBCOKNPMNFK": "Working on It",
    "icon": "UI_EmotionIcon374"
  },
  {
    "id": 24007,
    "IOCPLLBAMDH": 24,
    "CMCLFNNNLNL": 375,
    "NFMNMGAFIJI": 1292149160,
    "MBCOKNPMNFK": "Good Nara",
    "icon": "UI_EmotionIcon375"
  },
  {
    "id": 24008,
    "IOCPLLBAMDH": 24,
    "CMCLFNNNLNL": 376,
    "NFMNMGAFIJI": 4096032944,
    "MBCOKNPMNFK": "Bad Nara",
    "icon": "UI_EmotionIcon376"
  },
  {
    "id": 24009,
    "IOCPLLBAMDH": 24,
    "CMCLFNNNLNL": 377,
    "NFMNMGAFIJI": 3846390360,
    "MBCOKNPMNFK": "Do Go On",
    "icon": "UI_EmotionIcon377"
  },
  {
    "id": 24010,
    "IOCPLLBAMDH": 24,
    "CMCLFNNNLNL": 378,
    "NFMNMGAFIJI": 1786838448,
    "MBCOKNPMNFK": "Amazing",
    "icon": "UI_EmotionIcon378"
  },
  {
    "id": 24011,
    "IOCPLLBAMDH": 24,
    "CMCLFNNNLNL": 379,
    "NFMNMGAFIJI": 69145904,
    "MBCOKNPMNFK": "Friendship Comes First",
    "icon": "UI_EmotionIcon379"
  },
  {
    "id": 24012,
    "IOCPLLBAMDH": 24,
    "CMCLFNNNLNL": 380,
    "NFMNMGAFIJI": 2895972400,
    "MBCOKNPMNFK": "Amazing!",
    "icon": "UI_EmotionIcon380"
  },
  {
    "id": 24013,
    "IOCPLLBAMDH": 24,
    "CMCLFNNNLNL": 381,
    "NFMNMGAFIJI": 831545128,
    "MBCOKNPMNFK": "Don't Hold Back",
    "icon": "UI_EmotionIcon381"
  },
  {
    "id": 24014,
    "IOCPLLBAMDH": 24,
    "CMCLFNNNLNL": 382,
    "NFMNMGAFIJI": 707282752,
    "MBCOKNPMNFK": "Art!",
    "icon": "UI_EmotionIcon382"
  },
  {
    "id": 24015,
    "IOCPLLBAMDH": 24,
    "CMCLFNNNLNL": 383,
    "NFMNMGAFIJI": 3754648984,
    "MBCOKNPMNFK": "You Scared?",
    "icon": "UI_EmotionIcon383"
  },
  {
    "id": 24016,
    "IOCPLLBAMDH": 24,
    "CMCLFNNNLNL": 384,
    "NFMNMGAFIJI": 1222957656,
    "MBCOKNPMNFK": "You're Scared",
    "icon": "UI_EmotionIcon384"
  },
  {
    "id": 25001,
    "IOCPLLBAMDH": 25,
    "CMCLFNNNLNL": 385,
    "NFMNMGAFIJI": 3899161320,
    "MBCOKNPMNFK": "Refuse",
    "icon": "UI_EmotionIcon385"
  },
  {
    "id": 25002,
    "IOCPLLBAMDH": 25,
    "CMCLFNNNLNL": 386,
    "NFMNMGAFIJI": 4172137984,
    "MBCOKNPMNFK": "Shy",
    "icon": "UI_EmotionIcon386"
  },
  {
    "id": 25003,
    "IOCPLLBAMDH": 25,
    "CMCLFNNNLNL": 387,
    "NFMNMGAFIJI": 3640897632,
    "MBCOKNPMNFK": "Carsick",
    "icon": "UI_EmotionIcon387"
  },
  {
    "id": 25004,
    "IOCPLLBAMDH": 25,
    "CMCLFNNNLNL": 388,
    "NFMNMGAFIJI": 1505874200,
    "MBCOKNPMNFK": "Thinking",
    "icon": "UI_EmotionIcon388"
  },
  {
    "id": 25005,
    "IOCPLLBAMDH": 25,
    "CMCLFNNNLNL": 389,
    "NFMNMGAFIJI": 2868463264,
    "MBCOKNPMNFK": "I can do it",
    "icon": "UI_EmotionIcon389"
  },
  {
    "id": 25006,
    "IOCPLLBAMDH": 25,
    "CMCLFNNNLNL": 390,
    "NFMNMGAFIJI": 3086643544,
    "MBCOKNPMNFK": "Mimic",
    "icon": "UI_EmotionIcon390"
  },
  {
    "id": 25007,
    "IOCPLLBAMDH": 25,
    "CMCLFNNNLNL": 391,
    "NFMNMGAFIJI": 3391511904,
    "MBCOKNPMNFK": "It's you",
    "icon": "UI_EmotionIcon391"
  },
  {
    "id": 25008,
    "IOCPLLBAMDH": 25,
    "CMCLFNNNLNL": 392,
    "NFMNMGAFIJI": 4065280536,
    "MBCOKNPMNFK": "Go!",
    "icon": "UI_EmotionIcon392"
  },
  {
    "id": 25009,
    "IOCPLLBAMDH": 25,
    "CMCLFNNNLNL": 393,
    "NFMNMGAFIJI": 4096791120,
    "MBCOKNPMNFK": "Little Mage",
    "icon": "UI_EmotionIcon393"
  },
  {
    "id": 25010,
    "IOCPLLBAMDH": 25,
    "CMCLFNNNLNL": 394,
    "NFMNMGAFIJI": 1084712448,
    "MBCOKNPMNFK": "Frustrated",
    "icon": "UI_EmotionIcon394"
  },
  {
    "id": 25011,
    "IOCPLLBAMDH": 25,
    "CMCLFNNNLNL": 395,
    "NFMNMGAFIJI": 1040258472,
    "MBCOKNPMNFK": "Cooling down",
    "icon": "UI_EmotionIcon395"
  },
  {
    "id": 25012,
    "IOCPLLBAMDH": 25,
    "CMCLFNNNLNL": 396,
    "NFMNMGAFIJI": 3322615760,
    "MBCOKNPMNFK": "Heart-stealer",
    "icon": "UI_EmotionIcon396"
  },
  {
    "id": 25013,
    "IOCPLLBAMDH": 25,
    "CMCLFNNNLNL": 397,
    "NFMNMGAFIJI": 3170628296,
    "MBCOKNPMNFK": "Zoned out",
    "icon": "UI_EmotionIcon397"
  },
  {
    "id": 25014,
    "IOCPLLBAMDH": 25,
    "CMCLFNNNLNL": 398,
    "NFMNMGAFIJI": 382175976,
    "MBCOKNPMNFK": "Threatening",
    "icon": "UI_EmotionIcon398"
  },
  {
    "id": 25015,
    "IOCPLLBAMDH": 25,
    "CMCLFNNNLNL": 399,
    "NFMNMGAFIJI": 3924172936,
    "MBCOKNPMNFK": "I'm useless",
    "icon": "UI_EmotionIcon399"
  },
  {
    "id": 25016,
    "IOCPLLBAMDH": 25,
    "CMCLFNNNLNL": 400,
    "NFMNMGAFIJI": 262511632,
    "MBCOKNPMNFK": "Pass the buck",
    "icon": "UI_EmotionIcon400"
  },
  {
    "id": 26001,
    "IOCPLLBAMDH": 26,
    "CMCLFNNNLNL": 401,
    "NFMNMGAFIJI": 3105472808,
    "MBCOKNPMNFK": "Salute",
    "icon": "UI_EmotionIcon401"
  },
  {
    "id": 26002,
    "IOCPLLBAMDH": 26,
    "CMCLFNNNLNL": 402,
    "NFMNMGAFIJI": 1461897296,
    "MBCOKNPMNFK": "Debut",
    "icon": "UI_EmotionIcon402"
  },
  {
    "id": 26003,
    "IOCPLLBAMDH": 26,
    "CMCLFNNNLNL": 403,
    "NFMNMGAFIJI": 193943936,
    "MBCOKNPMNFK": "Nervous",
    "icon": "UI_EmotionIcon403"
  },
  {
    "id": 26004,
    "IOCPLLBAMDH": 26,
    "CMCLFNNNLNL": 404,
    "NFMNMGAFIJI": 1971778376,
    "MBCOKNPMNFK": "Surprise",
    "icon": "UI_EmotionIcon404"
  },
  {
    "id": 26005,
    "IOCPLLBAMDH": 26,
    "CMCLFNNNLNL": 405,
    "NFMNMGAFIJI": 3860210128,
    "MBCOKNPMNFK": "Watch the fun",
    "icon": "UI_EmotionIcon405"
  },
  {
    "id": 26006,
    "IOCPLLBAMDH": 26,
    "CMCLFNNNLNL": 406,
    "NFMNMGAFIJI": 2553591112,
    "MBCOKNPMNFK": "Standby Mode",
    "icon": "UI_EmotionIcon406"
  },
  {
    "id": 26007,
    "IOCPLLBAMDH": 26,
    "CMCLFNNNLNL": 407,
    "NFMNMGAFIJI": 1294953912,
    "MBCOKNPMNFK": "Gotcha",
    "icon": "UI_EmotionIcon407"
  },
  {
    "id": 26008,
    "IOCPLLBAMDH": 26,
    "CMCLFNNNLNL": 408,
    "NFMNMGAFIJI": 3561764424,
    "MBCOKNPMNFK": "Cheer",
    "icon": "UI_EmotionIcon408"
  },
  {
    "id": 26009,
    "IOCPLLBAMDH": 26,
    "CMCLFNNNLNL": 409,
    "NFMNMGAFIJI": 1407667984,
    "MBCOKNPMNFK": "Lurking",
    "icon": "UI_EmotionIcon409"
  },
  {
    "id": 26010,
    "IOCPLLBAMDH": 26,
    "CMCLFNNNLNL": 410,
    "NFMNMGAFIJI": 688226400,
    "MBCOKNPMNFK": "Popping in",
    "icon": "UI_EmotionIcon410"
  },
  {
    "id": 26011,
    "IOCPLLBAMDH": 26,
    "CMCLFNNNLNL": 411,
    "NFMNMGAFIJI": 1119758480,
    "MBCOKNPMNFK": "Alert",
    "icon": "UI_EmotionIcon411"
  },
  {
    "id": 26012,
    "IOCPLLBAMDH": 26,
    "CMCLFNNNLNL": 412,
    "NFMNMGAFIJI": 741735304,
    "MBCOKNPMNFK": "Hobby",
    "icon": "UI_EmotionIcon412"
  },
  {
    "id": 26013,
    "IOCPLLBAMDH": 26,
    "CMCLFNNNLNL": 413,
    "NFMNMGAFIJI": 688965368,
    "MBCOKNPMNFK": "Happy",
    "icon": "UI_EmotionIcon413"
  },
  {
    "id": 26014,
    "IOCPLLBAMDH": 26,
    "CMCLFNNNLNL": 414,
    "NFMNMGAFIJI": 2517562552,
    "MBCOKNPMNFK": "Refined",
    "icon": "UI_EmotionIcon414"
  },
  {
    "id": 26015,
    "IOCPLLBAMDH": 26,
    "CMCLFNNNLNL": 415,
    "NFMNMGAFIJI": 2847425640,
    "MBCOKNPMNFK": "Check please",
    "icon": "UI_EmotionIcon415"
  },
  {
    "id": 26016,
    "IOCPLLBAMDH": 26,
    "CMCLFNNNLNL": 416,
    "NFMNMGAFIJI": 4269516704,
    "MBCOKNPMNFK": "Bring it on",
    "icon": "UI_EmotionIcon416"
  }
]