[
  {
    "NKLFLJDJJBK": 1,
    "IMOKBFOCFOP": 97,
    "MGGPNIDOBGF": [
      {
        "CDOIPGMKDFF": 1
      },
      {
        "CDOIPGMKDFF": 2
      },
      {
        "CDOIPGMKDFF": 3
      }
    ],
    "EFPHEGPPCAJ": 2252948913,
    "MEGMECDBCCK": "Blossoms of Summer Night",
    "NCDLIKPCDMH": 3791680705,
    "CDJEJBPKNFE": "A secret pain lies buried under the towering giant tree beneath Mt. Hulao, where someone once sent an old friend off. Yet it was unavoidable, wasn't it? Whether they be gods or spirits, that which the years bring, the years must also take away in the end...",
    "IOIIGGHCBCP": 1505622105,
    "PFJKNCMANAF": "",
    "KLACPIPIEFP": 3660162380,
    "PJJEFCJPIGH": "",
    "GIOMHFAPLMK": 5072001,
    "GOMNCDKNDLG": [
      {
        "CDOIPGMKDFF": 15072001
      },
      {
        "CDOIPGMKDFF": 15072002
      },
      {
        "CDOIPGMKDFF": 15072003
      }
    ],
    "MHNMGOOAIDL": 0,
    "KOBOOPPPLEH": 30076,
    "ABIHPKCHHEI": 3
  },
  {
    "NKLFLJDJJBK": 2,
    "IMOKBFOCFOP": 89,
    "MGGPNIDOBGF": [
      {
        "CDOIPGMKDFF": 4
      },
      {
        "CDOIPGMKDFF": 5
      },
      {
        "CDOIPGMKDFF": 6
      }
    ],
    "EFPHEGPPCAJ": 405969929,
    "MEGMECDBCCK": "Time to Shine",
    "NCDLIKPCDMH": 648893881,
    "CDJEJBPKNFE": "Much difference there is in beholding Liyue from a distant mountain as opposed to overlooking the mortal realms from the clouds above. Yet wherever one might dwell, one's will to defend the land and guide its people shall never waver. Not in the slightest...",
    "IOIIGGHCBCP": 1501924937,
    "PFJKNCMANAF": "",
    "KLACPIPIEFP": 2139440820,
    "PJJEFCJPIGH": "",
    "GIOMHFAPLMK": 5072002,
    "GOMNCDKNDLG": [
      {
        "CDOIPGMKDFF": 15072004
      },
      {
        "CDOIPGMKDFF": 15072005
      },
      {
        "CDOIPGMKDFF": 15072006
      }
    ],
    "MHNMGOOAIDL": 0,
    "KOBOOPPPLEH": 30076,
    "ABIHPKCHHEI": 3
  },
  {
    "NKLFLJDJJBK": 3,
    "IMOKBFOCFOP": 88,
    "MGGPNIDOBGF": [
      {
        "CDOIPGMKDFF": 7
      },
      {
        "CDOIPGMKDFF": 8
      },
      {
        "CDOIPGMKDFF": 9
      }
    ],
    "EFPHEGPPCAJ": 417687081,
    "MEGMECDBCCK": "Drifter's Destiny",
    "NCDLIKPCDMH": 3810548329,
    "CDJEJBPKNFE": "The mountains to the south of Liyue are treacherous and barren, little-known and little-inhabited. Yet even in this corner of the world, the footprints of a character most diligent may be found. To her, perhaps, these are nothing more than baby steps compared to the path that lies ahead of Liyue.",
    "IOIIGGHCBCP": 3467694881,
    "PFJKNCMANAF": "",
    "KLACPIPIEFP": 1713615188,
    "PJJEFCJPIGH": "",
    "GIOMHFAPLMK": 5072003,
    "GOMNCDKNDLG": [
      {
        "CDOIPGMKDFF": 15072007
      },
      {
        "CDOIPGMKDFF": 15072008
      },
      {
        "CDOIPGMKDFF": 15072009
      }
    ],
    "MHNMGOOAIDL": 0,
    "KOBOOPPPLEH": 30076,
    "ABIHPKCHHEI": 3
  },
  {
    "NKLFLJDJJBK": 4,
    "IMOKBFOCFOP": 63,
    "MGGPNIDOBGF": [
      {
        "CDOIPGMKDFF": 10
      },
      {
        "CDOIPGMKDFF": 11
      },
      {
        "CDOIPGMKDFF": 12
      }
    ],
    "EFPHEGPPCAJ": 3326281001,
    "MEGMECDBCCK": "Devotion of the Keeper",
    "NCDLIKPCDMH": 3083282617,
    "CDJEJBPKNFE": "Just as evil must be conquered and filth must be cleansed, so too do silent sorrows, unfathomable solitude, and inexplicable resentment need redress. Scale the Wangshu Inn, which overlooks the peaceful lands of Liyue, with almond tofu as lovely as sweet dreams in your hand — and you too can help to resolve such problems...",
    "IOIIGGHCBCP": 2291195729,
    "PFJKNCMANAF": "",
    "KLACPIPIEFP": 3908364,
    "PJJEFCJPIGH": "",
    "GIOMHFAPLMK": 5072004,
    "GOMNCDKNDLG": [
      {
        "CDOIPGMKDFF": 15072010
      },
      {
        "CDOIPGMKDFF": 15072011
      },
      {
        "CDOIPGMKDFF": 15072012
      }
    ],
    "MHNMGOOAIDL": 0,
    "KOBOOPPPLEH": 30076,
    "ABIHPKCHHEI": 3
  },
  {
    "NKLFLJDJJBK": 5,
    "IMOKBFOCFOP": 88,
    "MGGPNIDOBGF": [
      {
        "CDOIPGMKDFF": 13
      },
      {
        "CDOIPGMKDFF": 14
      },
      {
        "CDOIPGMKDFF": 15
      }
    ],
    "EFPHEGPPCAJ": 2671706833,
    "MEGMECDBCCK": "Let's Go, Crimson Knight!",
    "NCDLIKPCDMH": 3900283305,
    "CDJEJBPKNFE": "The sacred and lovely Sangonomiya Shrine is the holy sanctum of Watatsumi's people. The Divine Priestess who dwells therein has inherited the will to protect this land. Even in this remote border realm far from Inazuma's center, this leader tirelessly seeks to bring peace and prosperity to her people...",
    "IOIIGGHCBCP": 1009410849,
    "PFJKNCMANAF": "",
    "KLACPIPIEFP": 1476137020,
    "PJJEFCJPIGH": "",
    "GIOMHFAPLMK": 5072005,
    "GOMNCDKNDLG": [
      {
        "CDOIPGMKDFF": 15072013
      },
      {
        "CDOIPGMKDFF": 15072014
      },
      {
        "CDOIPGMKDFF": 15072015
      }
    ],
    "MHNMGOOAIDL": 0,
    "KOBOOPPPLEH": 30076,
    "ABIHPKCHHEI": 3
  },
  {
    "NKLFLJDJJBK": 6,
    "IMOKBFOCFOP": 91,
    "MGGPNIDOBGF": [
      {
        "CDOIPGMKDFF": 16
      },
      {
        "CDOIPGMKDFF": 17
      },
      {
        "CDOIPGMKDFF": 18
      }
    ],
    "EFPHEGPPCAJ": 914578409,
    "MEGMECDBCCK": "Rage Beneath the Mountains",
    "NCDLIKPCDMH": 3376406801,
    "CDJEJBPKNFE": "\"They say that a great and mighty youkai dwells within Chinju Forest. It once waited for its good friend to return, but though it waited till the sun no longer rose, its friend returned not.\"\\n\"Did it eventually lose patience?\" The outlander Traveler asked.\\n\"I... I suppose it did, in the end...\" The young lady answered in her heart, her eyes lowered to the ground.",
    "IOIIGGHCBCP": 1820481761,
    "PFJKNCMANAF": "",
    "KLACPIPIEFP": 3044237172,
    "PJJEFCJPIGH": "",
    "GIOMHFAPLMK": 5072006,
    "GOMNCDKNDLG": [
      {
        "CDOIPGMKDFF": 15072016
      },
      {
        "CDOIPGMKDFF": 15072017
      },
      {
        "CDOIPGMKDFF": 15072018
      }
    ],
    "MHNMGOOAIDL": 0,
    "KOBOOPPPLEH": 30076,
    "ABIHPKCHHEI": 3
  },
  {
    "NKLFLJDJJBK": 7,
    "IMOKBFOCFOP": 83,
    "MGGPNIDOBGF": [
      {
        "CDOIPGMKDFF": 19
      },
      {
        "CDOIPGMKDFF": 20
      },
      {
        "CDOIPGMKDFF": 21
      }
    ],
    "EFPHEGPPCAJ": 1863780225,
    "MEGMECDBCCK": "Termination of Desires",
    "NCDLIKPCDMH": 3403246553,
    "CDJEJBPKNFE": "When eternity is no longer an obsession, when a god walks amongst mortals, when an answer is found to the question \"where to next?\" — Perhaps then, the Eternal Euthymia may truly become Inazuma's future...",
    "IOIIGGHCBCP": 1614871457,
    "PFJKNCMANAF": "",
    "KLACPIPIEFP": 3453372556,
    "PJJEFCJPIGH": "",
    "GIOMHFAPLMK": 5072007,
    "GOMNCDKNDLG": [
      {
        "CDOIPGMKDFF": 15072019
      },
      {
        "CDOIPGMKDFF": 15072020
      },
      {
        "CDOIPGMKDFF": 15072021
      }
    ],
    "MHNMGOOAIDL": 0,
    "KOBOOPPPLEH": 30076,
    "ABIHPKCHHEI": 3
  },
  {
    "NKLFLJDJJBK": 8,
    "IMOKBFOCFOP": 85,
    "MGGPNIDOBGF": [
      {
        "CDOIPGMKDFF": 22
      },
      {
        "CDOIPGMKDFF": 23
      },
      {
        "CDOIPGMKDFF": 24
      }
    ],
    "EFPHEGPPCAJ": 3585110825,
    "MEGMECDBCCK": "Invitation of Windblume",
    "NCDLIKPCDMH": 2930329953,
    "CDJEJBPKNFE": "Invitation of Windblume",
    "IOIIGGHCBCP": 3557350041,
    "PFJKNCMANAF": "",
    "KLACPIPIEFP": 1601178196,
    "PJJEFCJPIGH": "",
    "GIOMHFAPLMK": 2020201,
    "GOMNCDKNDLG": [
      {
        "CDOIPGMKDFF": 12020101
      },
      {
        "CDOIPGMKDFF": 12020102
      },
      {
        "CDOIPGMKDFF": 12020103
      }
    ],
    "MHNMGOOAIDL": 0,
    "KOBOOPPPLEH": 30046,
    "ABIHPKCHHEI": 3
  },
  {
    "NKLFLJDJJBK": 9,
    "IMOKBFOCFOP": 107,
    "MGGPNIDOBGF": [
      {
        "CDOIPGMKDFF": 25
      },
      {
        "CDOIPGMKDFF": 26
      },
      {
        "CDOIPGMKDFF": 27
      }
    ],
    "EFPHEGPPCAJ": 1811354729,
    "MEGMECDBCCK": "Contemplation in Snow",
    "NCDLIKPCDMH": 4027147561,
    "CDJEJBPKNFE": "Contemplation in Snow",
    "IOIIGGHCBCP": 246403209,
    "PFJKNCMANAF": "",
    "KLACPIPIEFP": 2388245092,
    "PJJEFCJPIGH": "",
    "GIOMHFAPLMK": 2020202,
    "GOMNCDKNDLG": [
      {
        "CDOIPGMKDFF": 12020104
      },
      {
        "CDOIPGMKDFF": 12020105
      },
      {
        "CDOIPGMKDFF": 12020106
      }
    ],
    "MHNMGOOAIDL": 0,
    "KOBOOPPPLEH": 30046,
    "ABIHPKCHHEI": 3
  },
  {
    "NKLFLJDJJBK": 10,
    "IMOKBFOCFOP": 108,
    "MGGPNIDOBGF": [
      {
        "CDOIPGMKDFF": 28
      },
      {
        "CDOIPGMKDFF": 29
      },
      {
        "CDOIPGMKDFF": 30
      }
    ],
    "EFPHEGPPCAJ": 1257206521,
    "MEGMECDBCCK": "Dance of Aphros",
    "NCDLIKPCDMH": 3885514769,
    "CDJEJBPKNFE": "Dance of Aphros",
    "IOIIGGHCBCP": 828547705,
    "PFJKNCMANAF": "",
    "KLACPIPIEFP": 1203555620,
    "PJJEFCJPIGH": "",
    "GIOMHFAPLMK": 2020203,
    "GOMNCDKNDLG": [
      {
        "CDOIPGMKDFF": 12020107
      },
      {
        "CDOIPGMKDFF": 12020108
      },
      {
        "CDOIPGMKDFF": 12020109
      }
    ],
    "MHNMGOOAIDL": 0,
    "KOBOOPPPLEH": 30046,
    "ABIHPKCHHEI": 3
  },
  {
    "NKLFLJDJJBK": 11,
    "IMOKBFOCFOP": 124,
    "MGGPNIDOBGF": [
      {
        "CDOIPGMKDFF": 31
      },
      {
        "CDOIPGMKDFF": 32
      },
      {
        "CDOIPGMKDFF": 33
      }
    ],
    "EFPHEGPPCAJ": 3146053401,
    "MEGMECDBCCK": "Caelestinum Finale Termini",
    "NCDLIKPCDMH": 4292682873,
    "CDJEJBPKNFE": "Caelestinum Finale Termini",
    "IOIIGGHCBCP": 216182961,
    "PFJKNCMANAF": "",
    "KLACPIPIEFP": 2900580084,
    "PJJEFCJPIGH": "",
    "GIOMHFAPLMK": 2020204,
    "GOMNCDKNDLG": [
      {
        "CDOIPGMKDFF": 12020110
      },
      {
        "CDOIPGMKDFF": 12020111
      },
      {
        "CDOIPGMKDFF": 12020112
      }
    ],
    "MHNMGOOAIDL": 0,
    "KOBOOPPPLEH": 30046,
    "ABIHPKCHHEI": 3
  },
  {
    "NKLFLJDJJBK": 12,
    "IMOKBFOCFOP": 71,
    "MGGPNIDOBGF": [
      {
        "CDOIPGMKDFF": 34
      },
      {
        "CDOIPGMKDFF": 35
      },
      {
        "CDOIPGMKDFF": 36
      }
    ],
    "EFPHEGPPCAJ": 1006001761,
    "MEGMECDBCCK": "Caprice of the Leaves",
    "NCDLIKPCDMH": 3935005865,
    "CDJEJBPKNFE": "Caprice of the Leaves",
    "IOIIGGHCBCP": 3593516969,
    "PFJKNCMANAF": "",
    "KLACPIPIEFP": 1956175396,
    "PJJEFCJPIGH": "",
    "GIOMHFAPLMK": 2020205,
    "GOMNCDKNDLG": [
      {
        "CDOIPGMKDFF": 12020113
      },
      {
        "CDOIPGMKDFF": 12020114
      },
      {
        "CDOIPGMKDFF": 12020115
      }
    ],
    "MHNMGOOAIDL": 0,
    "KOBOOPPPLEH": 30046,
    "ABIHPKCHHEI": 3
  },
  {
    "NKLFLJDJJBK": 13,
    "IMOKBFOCFOP": 120,
    "MGGPNIDOBGF": [
      {
        "CDOIPGMKDFF": 37
      },
      {
        "CDOIPGMKDFF": 38
      },
      {
        "CDOIPGMKDFF": 39
      }
    ],
    "EFPHEGPPCAJ": 4179711729,
    "MEGMECDBCCK": "Winding Through Avidya",
    "NCDLIKPCDMH": 115275161,
    "CDJEJBPKNFE": "Winding Through Avidya",
    "IOIIGGHCBCP": 1517613825,
    "PFJKNCMANAF": "",
    "KLACPIPIEFP": 2017411820,
    "PJJEFCJPIGH": "",
    "GIOMHFAPLMK": 2020206,
    "GOMNCDKNDLG": [
      {
        "CDOIPGMKDFF": 12020116
      },
      {
        "CDOIPGMKDFF": 12020117
      },
      {
        "CDOIPGMKDFF": 12020118
      }
    ],
    "MHNMGOOAIDL": 0,
    "KOBOOPPPLEH": 30046,
    "ABIHPKCHHEI": 3
  },
  {
    "NKLFLJDJJBK": 14,
    "IMOKBFOCFOP": 105,
    "MGGPNIDOBGF": [
      {
        "CDOIPGMKDFF": 40
      },
      {
        "CDOIPGMKDFF": 41
      },
      {
        "CDOIPGMKDFF": 42
      }
    ],
    "EFPHEGPPCAJ": 3350643041,
    "MEGMECDBCCK": "Bard's Adventure",
    "NCDLIKPCDMH": 2029111641,
    "CDJEJBPKNFE": "Bard's Adventure",
    "IOIIGGHCBCP": 4017174481,
    "PFJKNCMANAF": "",
    "KLACPIPIEFP": 150621420,
    "PJJEFCJPIGH": "",
    "GIOMHFAPLMK": 2020207,
    "GOMNCDKNDLG": [
      {
        "CDOIPGMKDFF": 12020119
      },
      {
        "CDOIPGMKDFF": 12020120
      },
      {
        "CDOIPGMKDFF": 12020121
      }
    ],
    "MHNMGOOAIDL": 0,
    "KOBOOPPPLEH": 30046,
    "ABIHPKCHHEI": 3
  }
]