[
  {
    "materialId": 10001,
    "LOICGJKJDDK": 101,
    "BBMGDDOIHDL": 100
  },
  {
    "materialId": 10002,
    "LOICGJKJDDK": 101,
    "BBMGDDOIHDL": 100
  },
  {
    "materialId": 10003,
    "LOICGJKJDDK": 101,
    "BBMGDDOIHDL": 100
  },
  {
    "materialId": 10004,
    "LOICGJKJDDK": 101,
    "BBMGDDOIHDL": 100
  },
  {
    "materialId": 10005,
    "LOICGJKJDDK": 101,
    "BBMGDDOIHDL": 100
  },
  {
    "materialId": 10006,
    "LOICGJKJDDK": 101,
    "BBMGDDOIHDL": 100
  },
  {
    "materialId": 10007,
    "LOICGJKJDDK": 101,
    "BBMGDDOIHDL": 100
  },
  {
    "materialId": 10008,
    "LOICGJKJDDK": 101,
    "BBMGDDOIHDL": 100
  },
  {
    "materialId": 10009,
    "LOICGJKJDDK": 101,
    "BBMGDDOIHDL": 100
  },
  {
    "materialId": 10010,
    "LOICGJKJDDK": 101,
    "BBMGDDOIHDL": 100
  },
  {
    "materialId": 10011,
    "LOICGJKJDDK": 101,
    "BBMGDDOIHDL": 100
  },
  {
    "materialId": 10012,
    "LOICGJKJDDK": 101,
    "BBMGDDOIHDL": 100
  },
  {
    "materialId": 10013,
    "LOICGJKJDDK": 101,
    "BBMGDDOIHDL": 100
  },
  {
    "materialId": 10014,
    "LOICGJKJDDK": 101,
    "BBMGDDOIHDL": 100
  },
  {
    "materialId": 10015,
    "LOICGJKJDDK": 101,
    "BBMGDDOIHDL": 100
  },
  {
    "materialId": 10016,
    "LOICGJKJDDK": 101,
    "BBMGDDOIHDL": 100
  },
  {
    "materialId": 10017,
    "LOICGJKJDDK": 101,
    "BBMGDDOIHDL": 100
  },
  {
    "materialId": 10018,
    "LOICGJKJDDK": 101,
    "BBMGDDOIHDL": 100
  },
  {
    "materialId": 10019,
    "LOICGJKJDDK": 101,
    "BBMGDDOIHDL": 100
  },
  {
    "materialId": 10020,
    "LOICGJKJDDK": 101,
    "BBMGDDOIHDL": 100
  },
  {
    "materialId": 10021,
    "LOICGJKJDDK": 101,
    "BBMGDDOIHDL": 100
  },
  {
    "materialId": 10022,
    "LOICGJKJDDK": 101,
    "BBMGDDOIHDL": 100
  },
  {
    "materialId": 10023,
    "LOICGJKJDDK": 101,
    "BBMGDDOIHDL": 100
  },
  {
    "materialId": 10024,
    "LOICGJKJDDK": 101,
    "BBMGDDOIHDL": 100
  },
  {
    "materialId": 10025,
    "LOICGJKJDDK": 101,
    "BBMGDDOIHDL": 100
  },
  {
    "materialId": 10026,
    "LOICGJKJDDK": 101,
    "BBMGDDOIHDL": 100
  },
  {
    "materialId": 10027,
    "LOICGJKJDDK": 101,
    "BBMGDDOIHDL": 100
  },
  {
    "materialId": 10028,
    "LOICGJKJDDK": 101,
    "BBMGDDOIHDL": 100
  },
  {
    "materialId": 10029,
    "LOICGJKJDDK": 101,
    "BBMGDDOIHDL": 100
  },
  {
    "materialId": 10030,
    "LOICGJKJDDK": 101,
    "BBMGDDOIHDL": 100
  },
  {
    "materialId": 10031,
    "LOICGJKJDDK": 101,
    "BBMGDDOIHDL": 100
  },
  {
    "materialId": 10032,
    "LOICGJKJDDK": 101,
    "BBMGDDOIHDL": 100
  },
  {
    "materialId": 10033,
    "LOICGJKJDDK": 101,
    "BBMGDDOIHDL": 100
  },
  {
    "materialId": 10034,
    "LOICGJKJDDK": 101,
    "BBMGDDOIHDL": 100
  },
  {
    "materialId": 10035,
    "LOICGJKJDDK": 101,
    "BBMGDDOIHDL": 100
  },
  {
    "materialId": 10036,
    "LOICGJKJDDK": 101,
    "BBMGDDOIHDL": 100
  },
  {
    "materialId": 10037,
    "LOICGJKJDDK": 101,
    "BBMGDDOIHDL": 100
  },
  {
    "materialId": 10038,
    "LOICGJKJDDK": 101,
    "BBMGDDOIHDL": 100
  },
  {
    "materialId": 10039,
    "LOICGJKJDDK": 101,
    "BBMGDDOIHDL": 100
  },
  {
    "materialId": 10040,
    "LOICGJKJDDK": 101,
    "BBMGDDOIHDL": 100
  },
  {
    "materialId": 10041,
    "LOICGJKJDDK": 101,
    "BBMGDDOIHDL": 100
  },
  {
    "materialId": 10042,
    "LOICGJKJDDK": 101,
    "BBMGDDOIHDL": 100
  },
  {
    "materialId": 10043,
    "LOICGJKJDDK": 101,
    "BBMGDDOIHDL": 100
  },
  {
    "materialId": 10044,
    "LOICGJKJDDK": 101,
    "BBMGDDOIHDL": 100
  },
  {
    "materialId": 10045,
    "LOICGJKJDDK": 101,
    "BBMGDDOIHDL": 100
  },
  {
    "materialId": 10046,
    "LOICGJKJDDK": 101,
    "BBMGDDOIHDL": 100
  },
  {
    "materialId": 10047,
    "LOICGJKJDDK": 101,
    "BBMGDDOIHDL": 100
  },
  {
    "materialId": 10048,
    "LOICGJKJDDK": 101,
    "BBMGDDOIHDL": 100
  },
  {
    "materialId": 10049,
    "LOICGJKJDDK": 101,
    "BBMGDDOIHDL": 100
  },
  {
    "materialId": 10050,
    "LOICGJKJDDK": 101,
    "BBMGDDOIHDL": 100
  },
  {
    "materialId": 10051,
    "LOICGJKJDDK": 101,
    "BBMGDDOIHDL": 100
  },
  {
    "materialId": 10052,
    "LOICGJKJDDK": 101,
    "BBMGDDOIHDL": 100
  },
  {
    "materialId": 10053,
    "LOICGJKJDDK": 101,
    "BBMGDDOIHDL": 100
  },
  {
    "materialId": 10054,
    "LOICGJKJDDK": 101,
    "BBMGDDOIHDL": 100
  },
  {
    "materialId": 10055,
    "LOICGJKJDDK": 101,
    "BBMGDDOIHDL": 100
  },
  {
    "materialId": 10056,
    "LOICGJKJDDK": 101,
    "BBMGDDOIHDL": 100
  },
  {
    "materialId": 10057,
    "LOICGJKJDDK": 101,
    "BBMGDDOIHDL": 100
  },
  {
    "materialId": 10058,
    "LOICGJKJDDK": 101,
    "BBMGDDOIHDL": 100
  },
  {
    "materialId": 10059,
    "LOICGJKJDDK": 101,
    "BBMGDDOIHDL": 100
  },
  {
    "materialId": 10060,
    "LOICGJKJDDK": 101,
    "BBMGDDOIHDL": 100
  },
  {
    "materialId": 10061,
    "LOICGJKJDDK": 101,
    "BBMGDDOIHDL": 100
  },
  {
    "materialId": 10062,
    "LOICGJKJDDK": 101,
    "BBMGDDOIHDL": 100
  },
  {
    "materialId": 10063,
    "LOICGJKJDDK": 101,
    "BBMGDDOIHDL": 100
  },
  {
    "materialId": 10064,
    "LOICGJKJDDK": 101,
    "BBMGDDOIHDL": 100
  },
  {
    "materialId": 10065,
    "LOICGJKJDDK": 101,
    "BBMGDDOIHDL": 100
  },
  {
    "materialId": 20001,
    "LOICGJKJDDK": 101,
    "BBMGDDOIHDL": 40
  },
  {
    "materialId": 20002,
    "LOICGJKJDDK": 101,
    "BBMGDDOIHDL": 40
  },
  {
    "materialId": 20003,
    "LOICGJKJDDK": 101,
    "BBMGDDOIHDL": 40
  },
  {
    "materialId": 20004,
    "LOICGJKJDDK": 101,
    "BBMGDDOIHDL": 40
  },
  {
    "materialId": 20005,
    "LOICGJKJDDK": 101,
    "BBMGDDOIHDL": 40
  },
  {
    "materialId": 20006,
    "LOICGJKJDDK": 101,
    "BBMGDDOIHDL": 40
  },
  {
    "materialId": 20007,
    "LOICGJKJDDK": 101,
    "BBMGDDOIHDL": 40
  },
  {
    "materialId": 20008,
    "LOICGJKJDDK": 101,
    "BBMGDDOIHDL": 40
  },
  {
    "materialId": 20009,
    "LOICGJKJDDK": 101,
    "BBMGDDOIHDL": 40
  },
  {
    "materialId": 20010,
    "LOICGJKJDDK": 101,
    "BBMGDDOIHDL": 40
  },
  {
    "materialId": 20011,
    "LOICGJKJDDK": 101,
    "BBMGDDOIHDL": 40
  },
  {
    "materialId": 20012,
    "LOICGJKJDDK": 101,
    "BBMGDDOIHDL": 40
  },
  {
    "materialId": 20013,
    "LOICGJKJDDK": 101,
    "BBMGDDOIHDL": 40
  },
  {
    "materialId": 20014,
    "LOICGJKJDDK": 101,
    "BBMGDDOIHDL": 40
  },
  {
    "materialId": 20015,
    "LOICGJKJDDK": 101,
    "BBMGDDOIHDL": 40
  },
  {
    "materialId": 20016,
    "LOICGJKJDDK": 101,
    "BBMGDDOIHDL": 40
  },
  {
    "materialId": 20017,
    "LOICGJKJDDK": 101,
    "BBMGDDOIHDL": 40
  },
  {
    "materialId": 20018,
    "LOICGJKJDDK": 101,
    "BBMGDDOIHDL": 40
  },
  {
    "materialId": 20019,
    "LOICGJKJDDK": 101,
    "BBMGDDOIHDL": 40
  },
  {
    "materialId": 20020,
    "LOICGJKJDDK": 101,
    "BBMGDDOIHDL": 40
  },
  {
    "materialId": 20021,
    "LOICGJKJDDK": 101,
    "BBMGDDOIHDL": 40
  },
  {
    "materialId": 20022,
    "LOICGJKJDDK": 101,
    "BBMGDDOIHDL": 40
  },
  {
    "materialId": 20023,
    "LOICGJKJDDK": 101,
    "BBMGDDOIHDL": 40
  },
  {
    "materialId": 20024,
    "LOICGJKJDDK": 101,
    "BBMGDDOIHDL": 40
  },
  {
    "materialId": 20025,
    "LOICGJKJDDK": 101,
    "BBMGDDOIHDL": 40
  },
  {
    "materialId": 20026,
    "LOICGJKJDDK": 101,
    "BBMGDDOIHDL": 40
  },
  {
    "materialId": 20027,
    "LOICGJKJDDK": 101,
    "BBMGDDOIHDL": 40
  },
  {
    "materialId": 20028,
    "LOICGJKJDDK": 101,
    "BBMGDDOIHDL": 40
  },
  {
    "materialId": 20029,
    "LOICGJKJDDK": 101,
    "BBMGDDOIHDL": 40
  },
  {
    "materialId": 30001,
    "LOICGJKJDDK": 101,
    "BBMGDDOIHDL": 20
  },
  {
    "materialId": 30002,
    "LOICGJKJDDK": 101,
    "BBMGDDOIHDL": 20
  },
  {
    "materialId": 30003,
    "LOICGJKJDDK": 101,
    "BBMGDDOIHDL": 20
  },
  {
    "materialId": 30004,
    "LOICGJKJDDK": 101,
    "BBMGDDOIHDL": 20
  },
  {
    "materialId": 30005,
    "LOICGJKJDDK": 101,
    "BBMGDDOIHDL": 20
  }
]