[
  {
    "level": 1,
    "LEBCENBBCHB": 70,
    "JMEJHADAECP": [
      {
        "CDOIPGMKDFF": 1
      }
    ],
    "CKHLLKPNMCF": 40,
    "IMNLGKBHCOH": 2000,
    "OFNGIFNLPPD": 10,
    "AAEKCOOEMEF": 0,
    "EDMGKPJLLIA": 0,
    "HOCOMFLHHFG": 40,
    "IIIPCHOGHAD": 0,
    "LDFIEIBHIFL": 0,
    "FNGBFENDCCA": 0,
    "IEJCIAJFEHA": 0,
    "KPGKKJJIFFN": 0
  },
  {
    "level": 2,
    "LEBCENBBCHB": 75,
    "JMEJHADAECP": [
      {
        "CDOIPGMKDFF": 2
      }
    ],
    "CKHLLKPNMCF": 50,
    "IMNLGKBHCOH": 4000,
    "OFNGIFNLPPD": 15,
    "AAEKCOOEMEF": 10,
    "EDMGKPJLLIA": 20,
    "HOCOMFLHHFG": 55,
    "IIIPCHOGHAD": 15,
    "LDFIEIBHIFL": 30,
    "FNGBFENDCCA": 20,
    "IEJCIAJFEHA": 8,
    "KPGKKJJIFFN": 10
  },
  {
    "level": 3,
    "LEBCENBBCHB": 80,
    "JMEJHADAECP": [
      {
        "CDOIPGMKDFF": 4
      }
    ],
    "CKHLLKPNMCF": 65,
    "IMNLGKBHCOH": 6000,
    "OFNGIFNLPPD": 20,
    "AAEKCOOEMEF": 20,
    "EDMGKPJLLIA": 40,
    "HOCOMFLHHFG": 70,
    "IIIPCHOGHAD": 30,
    "LDFIEIBHIFL": 60,
    "FNGBFENDCCA": 40,
    "IEJCIAJFEHA": 16,
    "KPGKKJJIFFN": 20
  },
  {
    "level": 4,
    "LEBCENBBCHB": 85,
    "JMEJHADAECP": [
      {
        "CDOIPGMKDFF": 6
      }
    ],
    "CKHLLKPNMCF": 80,
    "IMNLGKBHCOH": 8000,
    "OFNGIFNLPPD": 25,
    "AAEKCOOEMEF": 30,
    "EDMGKPJLLIA": 60,
    "HOCOMFLHHFG": 85,
    "IIIPCHOGHAD": 45,
    "LDFIEIBHIFL": 90,
    "FNGBFENDCCA": 60,
    "IEJCIAJFEHA": 24,
    "KPGKKJJIFFN": 30
  },
  {
    "level": 5,
    "LEBCENBBCHB": 90,
    "JMEJHADAECP": [
      {
        "CDOIPGMKDFF": 8
      }
    ],
    "CKHLLKPNMCF": 90,
    "IMNLGKBHCOH": 0,
    "OFNGIFNLPPD": 30,
    "AAEKCOOEMEF": 40,
    "EDMGKPJLLIA": 80,
    "HOCOMFLHHFG": 100,
    "IIIPCHOGHAD": 60,
    "LDFIEIBHIFL": 120,
    "FNGBFENDCCA": 80,
    "IEJCIAJFEHA": 32,
    "KPGKKJJIFFN": 40
  }
]